Workbook

Sheet WA_Fn-UseC_-HR-Employee-Attriti
A1: Age | B1: Attrition | C1: BusinessTravel | D1: DailyRate | E1: Department | F1: DistanceFromHome | G1: Education | H1: EducationField | I1: EmployeeCount | J1: EmployeeNumber | K1: EnvironmentSatisfaction | L1: Gender | M1: HourlyRate | N1: JobInvolvement | O1: JobLevel | P1: JobRole | Q1: JobSatisfaction | R1: MaritalStatus | S1: MonthlyIncome | T1: MonthlyRate | U1: NumCompaniesWorked | V1: Over18 | W1: OverTime | X1: PercentSalaryHike | Y1: PerformanceRating | Z1: RelationshipSatisfaction | AA1: StandardHours | AB1: StockOptionLevel | AC1: TotalWorkingYears | AD1: TrainingTimesLastYear | AE1: WorkLifeBalance | AF1: YearsAtCompany | AG1: YearsInCurrentRole | AH1: YearsSinceLastPromotion | AI1: YearsWithCurrManager
A2: 41 | B2: Yes | C2: Travel_Rarely | D2: 1102 | E2: Sales | F2: 1 | G2: 2 | H2: Life Sciences | I2: 1 | J2: 1 | K2: 2 | L2: Female | M2: 94 | N2: 3 | O2: 2 | P2: Sales Executive | Q2: 4 | R2: Single | S2: 5993 | T2: 19479 | U2: 8 | V2: Y | W2: Yes | X2: 11 | Y2: 3 | Z2: 1 | AA2: 80 | AB2: 0 | AC2: 8 | AD2: 0 | AE2: 1 | AF2: 6 | AG2: 4 | AH2: 0 | AI2: 5
A3: 49 | B3: No | C3: Travel_Frequently | D3: 279 | E3: Research & Development | F3: 8 | G3: 1 | H3: Life Sciences | I3: 1 | J3: 2 | K3: 3 | L3: Male | M3: 61 | N3: 2 | O3: 2 | P3: Research Scientist | Q3: 2 | R3: Married | S3: 5130 | T3: 24907 | U3: 1 | V3: Y | W3: No | X3: 23 | Y3: 4 | Z3: 4 | AA3: 80 | AB3: 1 | AC3: 10 | AD3: 3 | AE3: 3 | AF3: 10 | AG3: 7 | AH3: 1 | AI3: 7
A4: 37 | B4: Yes | C4: Travel_Rarely | D4: 1373 | E4: Research & Development | F4: 2 | G4: 2 | H4: Other | I4: 1 | J4: 4 | K4: 4 | L4: Male | M4: 92 | N4: 2 | O4: 1 | P4: Laboratory Technician | Q4: 3 | R4: Single | S4: 2090 | T4: 2396 | U4: 6 | V4: Y | W4: Yes | X4: 15 | Y4: 3 | Z4: 2 | AA4: 80 | AB4: 0 | AC4: 7 | AD4: 3 | AE4: 3 | AF4: 0 | AG4: 0 | AH4: 0 | AI4: 0
A5: 33 | B5: No | C5: Travel_Frequently | D5: 1392 | E5: Research & Development | F5: 3 | G5: 4 | H5: Life Sciences | I5: 1 | J5: 5 | K5: 4 | L5: Female | M5: 56 | N5: 3 | O5: 1 | P5: Research Scientist | Q5: 3 | R5: Married | S5: 2909 | T5: 23159 | U5: 1 | V5: Y | W5: Yes | X5: 11 | Y5: 3 | Z5: 3 | AA5: 80 | AB5: 0 | AC5: 8 | AD5: 3 | AE5: 3 | AF5: 8 | AG5: 7 | AH5: 3 | AI5: 0
A6: 27 | B6: No | C6: Travel_Rarely | D6: 591 | E6: Research & Development | F6: 2 | G6: 1 | H6: Medical | I6: 1 | J6: 7 | K6: 1 | L6: Male | M6: 40 | N6: 3 | O6: 1 | P6: Laboratory Technician | Q6: 2 | R6: Married | S6: 3468 | T6: 16632 | U6: 9 | V6: Y | W6: No | X6: 12 | Y6: 3 | Z6: 4 | AA6: 80 | AB6: 1 | AC6: 6 | AD6: 3 | AE6: 3 | AF6: 2 | AG6: 2 | AH6: 2 | AI6: 2
A7: 32 | B7: No | C7: Travel_Frequently | D7: 1005 | E7: Research & Development | F7: 2 | G7: 2 | H7: Life Sciences | I7: 1 | J7: 8 | K7: 4 | L7: Male | M7: 79 | N7: 3 | O7: 1 | P7: Laboratory Technician | Q7: 4 | R7: Single | S7: 3068 | T7: 11864 | U7: 0 | V7: Y | W7: No | X7: 13 | Y7: 3 | Z7: 3 | AA7: 80 | AB7: 0 | AC7: 8 | AD7: 2 | AE7: 2 | AF7: 7 | AG7: 7 | AH7: 3 | AI7: 6
A8: 59 | B8: No | C8: Travel_Rarely | D8: 1324 | E8: Research & Development | F8: 3 | G8: 3 | H8: Medical | I8: 1 | J8: 10 | K8: 3 | L8: Female | M8: 81 | N8: 4 | O8: 1 | P8: Laboratory Technician | Q8: 1 | R8: Married | S8: 2670 | T8: 9964 | U8: 4 | V8: Y | W8: Yes | X8: 20 | Y8: 4 | Z8: 1 | AA8: 80 | AB8: 3 | AC8: 12 | AD8: 3 | AE8: 2 | AF8: 1 | AG8: 0 | AH8: 0 | AI8: 0
A9: 30 | B9: No | C9: Travel_Rarely | D9: 1358 | E9: Research & Development | F9: 24 | G9: 1 | H9: Life Sciences | I9: 1 | J9: 11 | K9: 4 | L9: Male | M9: 67 | N9: 3 | O9: 1 | P9: Laboratory Technician | Q9: 3 | R9: Divorced | S9: 2693 | T9: 13335 | U9: 1 | V9: Y | W9: No | X9: 22 | Y9: 4 | Z9: 2 | AA9: 80 | AB9: 1 | AC9: 1 | AD9: 2 | AE9: 3 | AF9: 1 | AG9: 0 | AH9: 0 | AI9: 0
A10: 38 | B10: No | C10: Travel_Frequently | D10: 216 | E10: Research & Development | F10: 23 | G10: 3 | H10: Life Sciences | I10: 1 | J10: 12 | K10: 4 | L10: Male | M10: 44 | N10: 2 | O10: 3 | P10: Manufacturing Director | Q10: 3 | R10: Single | S10: 9526 | T10: 8787 | U10: 0 | V10: Y | W10: No | X10: 21 | Y10: 4 | Z10: 2 | AA10: 80 | AB10: 0 | AC10: 10 | AD10: 2 | AE10: 3 | AF10: 9 | AG10: 7 | AH10: 1 | AI10: 8
A11: 36 | B11: No | C11: Travel_Rarely | D11: 1299 | E11: Research & Development | F11: 27 | G11: 3 | H11: Medical | I11: 1 | J11: 13 | K11: 3 | L11: Male | M11: 94 | N11: 3 | O11: 2 | P11: Healthcare Representative | Q11: 3 | R11: Married | S11: 5237 | T11: 16577 | U11: 6 | V11: Y | W11: No | X11: 13 | Y11: 3 | Z11: 2 | AA11: 80 | AB11: 2 | AC11: 17 | AD11: 3 | AE11: 2 | AF11: 7 | AG11: 7 | AH11: 7 | AI11: 7
A12: 35 | B12: No | C12: Travel_Rarely | D12: 809 | E12: Research & Development | F12: 16 | G12: 3 | H12: Medical | I12: 1 | J12: 14 | K12: 1 | L12: Male | M12: 84 | N12: 4 | O12: 1 | P12: Laboratory Technician | Q12: 2 | R12: Married | S12: 2426 | T12: 16479 | U12: 0 | V12: Y | W12: No | X12: 13 | Y12: 3 | Z12: 3 | AA12: 80 | AB12: 1 | AC12: 6 | AD12: 5 | AE12: 3 | AF12: 5 | AG12: 4 | AH12: 0 | AI12: 3
A13: 29 | B13: No | C13: Travel_Rarely | D13: 153 | E13: Research & Development | F13: 15 | G13: 2 | H13: Life Sciences | I13: 1 | J13: 15 | K13: 4 | L13: Female | M13: 49 | N13: 2 | O13: 2 | P13: Laboratory Technician | Q13: 3 | R13: Single | S13: 4193 | T13: 12682 | U13: 0 | V13: Y | W13: Yes | X13: 12 | Y13: 3 | Z13: 4 | AA13: 80 | AB13: 0 | AC13: 10 | AD13: 3 | AE13: 3 | AF13: 9 | AG13: 5 | AH13: 0 | AI13: 8
... A1471: 34 | B1471: No | C1471: Travel_Rarely | D1471: 628 | E1471: Research & Development | F1471: 8 | G1471: 3 | H1471: Medical | I1471: 1 | J1471: 2068 | K1471: 2 | L1471: Male | M1471: 82 | N1471: 4 | O1471: 2 | P1471: Laboratory Technician | Q1471: 3 | R1471: Married | S1471: 4404 | T1471: 10228 | U1471: 2 | V1471: Y | W1471: No | X1471: 12 | Y1471: 3 | Z1471: 1 | AA1471: 80 | AB1471: 0 | AC1471: 6 | AD1471: 3 | AE1471: 4 | AF1471: 4 | AG1471: 3 | AH1471: 1 | AI1471: 2

Sheet Dataset_Overview
A1: HR EMPLOYEE ATTRITION ANALYTICS PROJECT — DATASET OVERVIEW & JUSTIFICATION
A3: Dataset Name | B3: IBM HR Analytics Employee Attrition & Performance
A4: Source | B4: Kaggle (fictional dataset created by IBM data scientists)
A5: Link | B5: https://www.kaggle.com/datasets/pavansubhasht/ibm-hr-analytics-attrition-dataset
A6: Records | B6: =COUNTA(Data_RawIssues!A:A)-1 -> 1485
A7: Columns | B7: 35
A9: BUSINESS CONTEXT
A10: Employee attrition (voluntary/involuntary turnover) is one of the costliest problems in workforce management. Industry studies estimate replacing a single employee costs 50%-200% of their annual salary once recruiting, onboarding, lost productivity and knowledge loss are accounted for. IBM compiled this dataset (with fictional but realistic employee records) to let analysts study the drivers of attrition across a large, multi-department organization spanning Sales, Research & Development, and Human Resources.
A12: BUSINESS PROBLEM
A13: HR leadership needs to understand which employees are at the highest risk of leaving, why they leave, and which levers (compensation, work-life balance, career progression, overtime policy) the company can pull to retain high-value talent before attrition happens rather than reacting after the fact.
A15: ANALYTICAL OBJECTIVES
A16: 1. Quantify attrition rate overall and by department, job role, and demographic segment.
A17: 2. Identify the strongest statistical drivers of attrition (satisfaction, income, overtime, tenure, commute distance, promotion history).
A18: 3. Build a predictive model that flags individual employees at elevated attrition risk.
A19: 4. Translate findings into KPIs and a monitoring dashboard for ongoing HR decision-making.
A21: WHY THE TARGET VARIABLE (Attrition) IS SUITABLE
A22: Attrition is a binary Yes/No field recorded for every employee, giving a clean, unambiguous label for supervised classification. It is directly actionable (HR can intervene on a per-employee basis), commercially meaningful (turnover cost is a measurable P&L line), and it is influenced by a rich mix of numeric (income, tenure, satisfaction scores) and categorical (department, job role, marital status, overtime) predictors, making it ideal for both statistical EDA and machine learning.
A24: WHY THIS DATASET IS APPROPRIATE
... A28: A working attrition-risk model lets HR prioritize retention spend (counter-offers, flexible work, promotion cycles) on the employees most likely to leave, rather than applying blanket policies. Even a modest reduction in voluntary attrition among high performers translates directly into avoided replacement cost, preserved institutional knowledge, and improved team morale.

Sheet Cleaning_Log
A1: DATA CLEANING LOG
A2: Source: Data_RawIssues (1,485 rows incl. 15 injected duplicates) → Output: Data_Cleaned (1,470 rows)
A4: # | B4: Issue Type | C4: Column(s) Affected | D4: Count | E4: Why It Matters | F4: Example BEFORE | G4: Cleaning Action | H4: Example AFTER
A5: 1 | B5: Missing values | C5: MonthlyIncome, EnvironmentSatisfaction, Department, TotalWorkingYears, BusinessTravel | D5: 40 | E5: Blanks break aggregation (SUM/AVERAGE silently skip or error) and would bias any ML model trained on incomplete rows. | F5: Data_RawIssues!S12 = (blank) | G5: Numeric fields imputed with median (overall or by JobLevel); categorical fields imputed with mode (most frequent category). | H5: Data_Cleaned!S11 = 5343 (JobLevel-2 median income)
A6: 2 | B6: Duplicate records | C6: All 35 columns (whole row) | D6: 15 | E6: Duplicate employee rows double-count that person in headcount, attrition-rate and payroll aggregations, inflating every downstream metric. | F6: EmployeeNumber 8 appears in rows 9 and 1472 | G6: Dropped duplicate rows, keeping first occurrence per EmployeeNumber (drop_duplicates(subset='EmployeeNumber', keep='first')). | H6: 1,485 rows → 1,470 unique employees
A7: 3 | B7: Inconsistent categorical text | C7: Department, Gender, OverTime, MaritalStatus, BusinessTravel | D7: 21 | E7: "Sales", "sales", "SALES" and "Sales " are treated as 4 distinct categories by GROUP BY/pivot logic and by one-hot encoders, fragmenting the true signal. | F7: Data_RawIssues!E102 = "sales"; E202="SALES"; E302="Research & Development " | G7: Trimmed whitespace, standardized casing, and mapped abbreviations/synonyms to one canonical label per category via a lookup dictionary. | H7: Data_Cleaned!E101 = "Sales" (all variants unified)
A8: 4 | B8: Incorrect data types (numbers stored as text) | C8: Age, MonthlyIncome, DistanceFromHome, PercentSalaryHike | D8: 10 | E8: Text-typed numerics fail arithmetic and are silently excluded from SUM/AVERAGE/correlation calculations, and break ML feature matrices which require numeric dtypes. | F8: Data_RawIssues!A27 = "35 years"; S56="$5,993"; S76="6500 USD" | G8: Extracted the numeric substring (regex \d+), stripped currency symbols/commas/unit suffixes, cast to float/int. | H8: Data_Cleaned!A26 = 35 (numeric)
A9: 5 | B9: Outliers | C9: Age, MonthlyIncome, DistanceFromHome, NumCompaniesWorked, TotalWorkingYears | D9: 8 | E9: Implausible values (Age=202, MonthlyIncome=$999,999, negative commute distance) distort means/std-devs and can dominate distance-based models or tree splits. | F9: Data_RawIssues!A502=150; A602=202; A702=-5; S802=999999; S902=100; F1002=-10; U1102=99; AC1202=80 | G9: Applied business-rule bounds (Age 18-75, MonthlyIncome $1,000-$20,000, TotalWorkingYears ≤ 45, NumCompaniesWorked ≤ 15). Values outside bounds treated as missing, then median-imputed. Negative DistanceFromHome corrected via absolute value (sign-flip error). | H9: Data_Cleaned!A501=36 (median); S801=9950 (JobLevel median); F1001=10
A10: 6 | B10: Scale/unit corruption (percentage stored as decimal fraction) | C10: PercentSalaryHike | D10: 2 | E10: Discovered during verification: when the injected text values "11%"/"14%" were entered into a spreadsheet cell, Excel auto-parsed them as percentage-formatted numbers (0.11 / 0.14) rather than the whole numbers 11 / 14. This is a common real-world spreadsheet data-entry trap that silently divides values by 100. | F10: Data_RawIssues!X107 = 0.11 (displayed as "11%") | G10: Applied a rule: any PercentSalaryHike value < 1 (outside the column's natural 11-25 range) is a scale error — multiplied by 100 and reformatted as a whole number. | H10: Data_Cleaned!X106 = 11
A12: EQUIVALENT PYTHON (PANDAS/NUMPY) CLEANING PIPELINE
A13: import pandas as pd import numpy as np import re df = pd.read_csv('HR_Employee_Attrition_RawIssues.csv') print(df.shape) # (1485, 35) -- includes 15 injected duplicates print(df.dtypes) print(df.isnull().sum()) # missing-value audit # --- 1. Fix incorrect data types (strip units/currency, cast to numeric) --- def to_numeric(series): return series.apply(lambda v: float(re.search(r'-?\d+(\.\d+)?', str(v).replace(',', '')).group()) if pd.notna(v) and str(v).strip() != '' else np.nan) for col in ['Age', 'MonthlyIncome', 'DistanceFromHome', 'PercentSalaryHike']: df[col] = to_numeric(df[col]) # --- 2. Standardize inconsistent categorical text --- def clean_cat(series, mapping): s = series.astype(str).str.strip().str.lower() return s.map(mapping).fillna(series.astype(str).str.strip()) dept_map = {'sales': 'Sales', 'research & development': 'Research & Development', 'human resources': 'Human Resources', 'r&d': 'Research & Development'} gender_map = {'m': 'Male', 'f': 'Female', 'male': 'Male', 'female': 'Female'} overtime_map = {'yes': 'Yes', 'no': 'No'} marital_map = {'single': 'Single', 'married': 'Married', 'divorced': 'Divorced'} travel_map = {'travel_rarely': 'Travel_Rarely', 'travel_frequently': 'Travel_Frequently', 'non-travel': 'Non-Travel'} df['Department'] = clean_cat(df['Department'], dept_map) df['Gender'] = clean_cat(df['Gender'], gender_map) df['OverTime'] = clean_cat(df['OverTime'], overtime_map) df['MaritalStatus'] = clean_cat(df['MaritalStatus'], marital_map) df['BusinessTravel'] = clean_cat(df['BusinessTravel'], travel_map) # --- 3. Outlier detection & correction (business-rule bounds) --- df.loc[(df['Age'] < 18) | (df['Age'] > 75), 'Age'] = np.nan df.loc[(df['MonthlyIncome'] < 1000) | (df['MonthlyIncome'] > 20000), 'MonthlyIncome'] = np.nan df.loc[df['NumCompaniesWorked'] > 15, 'NumCompaniesWorked'] = np.nan df.loc[df['TotalWorkingYears'] > 45, 'TotalWorkingYears'] = np.nan df['DistanceFromHome'] = df['DistanceFromHome'].abs() # sign-flip correction # --- 4. Impute missing values (median for numeric, mode for categorical) --- df['Age'] = df['Age'].fillna(df['Age'].median()) df['MonthlyIncome'] = df.groupby('JobLevel')['MonthlyIncome'].transform(lambda x: x.fillna(x.median())) df['TotalWorkingYears'] = df['TotalWorkingYears'].fillna(df['TotalWorkingYears'].median()) df['NumCompaniesWorked'] = df['NumCompaniesWorked'].fillna(df['NumCompaniesWorked'].median()) df['EnvironmentSatisfaction'] = df['EnvironmentSatisfaction'].fillna(df['EnvironmentSatisfaction'].mode()[0]) df['Department'] = df['Department'].fillna(df['Department'].mode()[0]) df['BusinessTravel'] = df['BusinessTravel'].fillna(df['BusinessTravel'].mode()[0]) # --- 5. Remove duplicate records --- df = df.drop_duplicates(subset='EmployeeNumber', keep='first') print(df.shape) # (1470, 35) # --- 6. Encode categorical variables --- df['Attrition_Flag'] = (df['Attrition'] == 'Yes').astype(int) df['OverTime_Flag'] = (df['OverTime'] == 'Yes').astype(int) df_encoded = pd.get_dummies(df, columns=['Department', 'JobRole', 'MaritalStatus', 'EducationField', 'BusinessTravel', 'Gender'], drop_first=True) # --- 7. Feature scaling (for distance-based/linear models) --- from sklearn.preprocessing import StandardScaler num_cols = ['MonthlyIncome', 'Age', 'DistanceFromHome', 'TotalWorkingYears'] scaler = StandardScaler() df_encoded[[c + '_scaled' for c in num_cols]] = scaler.fit_transform(df_encoded[num_cols]) # --- 8. Feature engineering --- df['SatisfactionIndex'] = df[['EnvironmentSatisfaction','JobSatisfaction', 'RelationshipSatisfaction','WorkLifeBalance']].mean(axis=1) df['IncomePerYearAtCompany'] = df['MonthlyIncome'] * 12 / (df['YearsAtCompany'] + 1) df['TenureRatio'] = df['YearsAtCompany'] / (df['TotalWorkingYears'] + 1) df['AgeGroup'] = pd.cut(df['Age'], bins=[0,30,40,50,100], labels=['Under 30','30-39','40-49','50+']) df['IncomeBand'] = pd.qcut(df['MonthlyIncome'], 4, labels=['Low','Medium','High','Very High']) df.to_csv('HR_Employee_Attrition_Cleaned.csv', index=False)
A15: AI-ASSISTED RECOMMENDATIONS FOR FURTHER DATA QUALITY IMPROVEMENT
A16: 1. Add data-entry validation (dropdown lists / controlled vocabularies) at the HRIS source system for Department, Gender, MaritalStatus, BusinessTravel and OverTime to prevent free-text variants from ever entering the warehouse.
A17: 2. Enforce numeric field types at ingestion (schema validation e.g. Great Expectations / Pandera) so Age, MonthlyIncome, DistanceFromHome and PercentSalaryHike cannot be saved as text with units or currency symbols.
A18: 3. Add a uniqueness constraint on EmployeeNumber in the source database to block duplicate record insertion at the point of entry rather than relying on downstream de-duplication.
A19: 4. Implement automated range checks (e.g. Age 18-75, MonthlyIncome within organizational pay bands) as a nightly data-quality job, flagging violations for HR review before they reach analytics tables.
A20: 5. Track a data-quality score per refresh (missing %, duplicate %, out-of-range %) on a monitoring dashboard so degradation is caught immediately rather than discovered during analysis.
A21: 6. For MonthlyIncome imputation specifically, prefer group-wise (JobLevel) medians over a single global median — income varies enormously by level, and a global median would systematically misstate compensation for junior/senior employees alike.

Sheet Data_RawIssues
A1: Age | B1: Attrition | C1: BusinessTravel | D1: DailyRate | E1: Department | F1: DistanceFromHome | G1: Education | H1: EducationField | I1: EmployeeCount | J1: EmployeeNumber | K1: EnvironmentSatisfaction | L1: Gender | M1: HourlyRate | N1: JobInvolvement | O1: JobLevel | P1: JobRole | Q1: JobSatisfaction | R1: MaritalStatus | S1: MonthlyIncome | T1: MonthlyRate | U1: NumCompaniesWorked | V1: Over18 | W1: OverTime | X1: PercentSalaryHike | Y1: PerformanceRating | Z1: RelationshipSatisfaction | AA1: StandardHours | AB1: StockOptionLevel | AC1: TotalWorkingYears | AD1: TrainingTimesLastYear | AE1: WorkLifeBalance | AF1: YearsAtCompany | AG1: YearsInCurrentRole | AH1: YearsSinceLastPromotion | AI1: YearsWithCurrManager
A2: 41 | B2: Yes | C2: Travel_Rarely | D2: 1102 | E2: Sales | F2: 1 | G2: 2 | H2: Life Sciences | I2: 1 | J2: 1 | K2: 2 | L2: Female | M2: 94 | N2: 3 | O2: 2 | P2: Sales Executive | Q2: 4 | R2: Single | S2: 5993 | T2: 19479 | U2: 8 | V2: Y | W2: Yes | X2: 11 | Y2: 3 | Z2: 1 | AA2: 80 | AB2: 0 | AC2: 8 | AD2: 0 | AE2: 1 | AF2: 6 | AG2: 4 | AH2: 0 | AI2: 5
A3: 49 | B3: No | C3: Travel_Frequently | D3: 279 | E3: Research & Development | F3: 8 | G3: 1 | H3: Life Sciences | I3: 1 | J3: 2 | K3: 3 | L3: Male | M3: 61 | N3: 2 | O3: 2 | P3: Research Scientist | Q3: 2 | R3: Married | S3: 5130 | T3: 24907 | U3: 1 | V3: Y | W3: No | X3: 23 | Y3: 4 | Z3: 4 | AA3: 80 | AB3: 1 | AC3: 10 | AD3: 3 | AE3: 3 | AF3: 10 | AG3: 7 | AH3: 1 | AI3: 7
A4: 37 | B4: Yes | C4: Travel_Rarely | D4: 1373 | E4: Research & Development | F4: 2 | G4: 2 | H4: Other | I4: 1 | J4: 4 | K4: 4 | L4: Male | M4: 92 | N4: 2 | O4: 1 | P4: Laboratory Technician | Q4: 3 | R4: Single | S4: 2090 | T4: 2396 | U4: 6 | V4: Y | W4: Yes | X4: 15 | Y4: 3 | Z4: 2 | AA4: 80 | AB4: 0 | AC4: 7 | AD4: 3 | AE4: 3 | AF4: 0 | AG4: 0 | AH4: 0 | AI4: 0
A5: 33 | B5: No | C5: Travel_Frequently | D5: 1392 | E5: Research & Development | F5: 3 | G5: 4 | H5: Life Sciences | I5: 1 | J5: 5 | K5: 4 | L5: Female | M5: 56 | N5: 3 | O5: 1 | P5: Research Scientist | Q5: 3 | R5: Married | S5: 2909 | T5: 23159 | U5: 1 | V5: Y | W5: Yes | X5: 11 | Y5: 3 | Z5: 3 | AA5: 80 | AB5: 0 | AC5: 8 | AD5: 3 | AE5: 3 | AF5: 8 | AG5: 7 | AH5: 3 | AI5: 0
A6: 27 | B6: No | C6: Travel_Rarely | D6: 591 | E6: Research & Development | F6: 2 | G6: 1 | H6: Medical | I6: 1 | J6: 7 | K6: 1 | L6: Male | M6: 40 | N6: 3 | O6: 1 | P6: Laboratory Technician | Q6: 2 | R6: Married | S6: 3468 | T6: 16632 | U6: 9 | V6: Y | W6: No | X6: 12 | Y6: 3 | Z6: 4 | AA6: 80 | AB6: 1 | AC6: 6 | AD6: 3 | AE6: 3 | AF6: 2 | AG6: 2 | AH6: 2 | AI6: 2
A7: 32 | B7: No | C7: Travel_Frequently | D7: 1005 | E7: Research & Development | F7: 2 | G7: 2 | H7: Life Sciences | I7: 1 | J7: 8 | K7: 4 | L7: Male | M7: 79 | N7: 3 | O7: 1 | P7: Laboratory Technician | Q7: 4 | R7: Single | S7: 3068 | T7: 11864 | U7: 0 | V7: Y | W7: No | X7: 13 | Y7: 3 | Z7: 3 | AA7: 80 | AB7: 0 | AC7: 8 | AD7: 2 | AE7: 2 | AF7: 7 | AG7: 7 | AH7: 3 | AI7: 6
A8: 59 | B8: No | C8: Travel_Rarely | D8: 1324 | E8: Research & Development | F8: 3 | G8: 3 | H8: Medical | I8: 1 | J8: 10 | K8: 3 | L8: Female | M8: 81 | N8: 4 | O8: 1 | P8: Laboratory Technician | Q8: 1 | R8: Married | S8: 2670 | T8: 9964 | U8: 4 | V8: Y | W8: Yes | X8: 20 | Y8: 4 | Z8: 1 | AA8: 80 | AB8: 3 | AC8: 12 | AD8: 3 | AE8: 2 | AF8: 1 | AG8: 0 | AH8: 0 | AI8: 0
A9: 30 | B9: No | C9: Travel_Rarely | D9: 1358 | E9: Research & Development | F9: 24 | G9: 1 | H9: Life Sciences | I9: 1 | J9: 11 | K9: 4 | L9: Male | M9: 67 | N9: 3 | O9: 1 | P9: Laboratory Technician | Q9: 3 | R9: Divorced | S9: 2693 | T9: 13335 | U9: 1 | V9: Y | W9: No | X9: 22 | Y9: 4 | Z9: 2 | AA9: 80 | AB9: 1 | AC9: 1 | AD9: 2 | AE9: 3 | AF9: 1 | AG9: 0 | AH9: 0 | AI9: 0
A10: 38 | B10: No | C10: Travel_Frequently | D10: 216 | E10: Research & Development | F10: 23 | G10: 3 | H10: Life Sciences | I10: 1 | J10: 12 | K10: 4 | L10: Male | M10: 44 | N10: 2 | O10: 3 | P10: Manufacturing Director | Q10: 3 | R10: Single | S10: 9526 | T10: 8787 | U10: 0 | V10: Y | W10: No | X10: 21 | Y10: 4 | Z10: 2 | AA10: 80 | AB10: 0 | AC10: 10 | AD10: 2 | AE10: 3 | AF10: 9 | AG10: 7 | AH10: 1 | AI10: 8
A11: 36 | B11: No | C11: Travel_Rarely | D11: 1299 | E11: Research & Development | F11: 27 | G11: 3 | H11: Medical | I11: 1 | J11: 13 | K11: 3 | L11: Male | M11: 94 | N11: 3 | O11: 2 | P11: Healthcare Representative | Q11: 3 | R11: Married | S11: 5237 | T11: 16577 | U11: 6 | V11: Y | W11: No | X11: 13 | Y11: 3 | Z11: 2 | AA11: 80 | AB11: 2 | AC11: 17 | AD11: 3 | AE11: 2 | AF11: 7 | AG11: 7 | AH11: 7 | AI11: 7
A12: 35 | B12: No | C12: Travel_Rarely | D12: 809 | E12: Research & Development | F12: 16 | G12: 3 | H12: Medical | I12: 1 | J12: 14 | K12: 1 | L12: Male | M12: 84 | N12: 4 | O12: 1 | P12: Laboratory Technician | Q12: 2 | R12: Married | T12: 16479 | U12: 0 | V12: Y | W12: No | X12: 13 | Y12: 3 | Z12: 3 | AA12: 80 | AB12: 1 | AC12: 6 | AD12: 5 | AE12: 3 | AF12: 5 | AG12: 4 | AH12: 0 | AI12: 3
A13: 29 | B13: No | C13: Travel_Rarely | D13: 153 | E13: Research & Development | F13: 15 | G13: 2 | H13: Life Sciences | I13: 1 | J13: 15 | K13: 4 | L13: Female | M13: 49 | N13: 2 | O13: 2 | P13: Laboratory Technician | Q13: 3 | R13: Single | S13: 4193 | T13: 12682 | U13: 0 | V13: Y | W13: Yes | X13: 12 | Y13: 3 | Z13: 4 | AA13: 80 | AB13: 0 | AC13: 10 | AD13: 3 | AE13: 3 | AF13: 9 | AG13: 5 | AH13: 0 | AI13: 8
A14: 31 | B14: No | C14: Travel_Rarely | D14: 670 | E14: Research & Development | F14: 26 | G14: 1 | H14: Life Sciences | I14: 1 | J14: 16 | K14: 1 | L14: Male | M14: 31 | N14: 3 | O14: 1 | P14: Research Scientist | Q14: 3 | R14: Divorced | S14: 2911 | T14: 15170 | U14: 1 | V14: Y | W14: No | X14: 17 | Y14: 3 | Z14: 4 | AA14: 80 | AB14: 1 | AC14: 5 | AD14: 1 | AE14: 2 | AF14: 5 | AG14: 2 | AH14: 4 | AI14: 3
A15: 34 | B15: No | C15: Travel_Rarely | D15: 1346 | E15: Research & Development | F15: 19 | G15: 2 | H15: Medical | I15: 1 | J15: 18 | K15: 2 | L15: Male | M15: 93 | N15: 3 | O15: 1 | P15: Laboratory Technician | Q15: 4 | R15: Divorced | S15: 2661 | T15: 8758 | U15: 0 | V15: Y | W15: No | X15: 11 | Y15: 3 | Z15: 3 | AA15: 80 | AB15: 1 | AC15: 3 | AD15: 2 | AE15: 3 | AF15: 2 | AG15: 2 | AH15: 1 | AI15: 2
A16: 28 | B16: Yes | C16: Travel_Rarely | D16: 103 | E16: Research & Development | F16: 24 | G16: 3 | H16: Life Sciences | I16: 1 | J16: 19 | K16: 3 | L16: Male | M16: 50 | N16: 2 | O16: 1 | P16: Laboratory Technician | Q16: 3 | R16: Single | S16: 2028 | T16: 12947 | U16: 5 | V16: Y | W16: Yes | X16: 14 | Y16: 3 | Z16: 2 | AA16: 80 | AB16: 0 | AC16: 6 | AD16: 4 | AE16: 3 | AF16: 4 | AG16: 2 | AH16: 0 | AI16: 3
A17: 29 | B17: No | C17: Travel_Rarely | D17: 1389 | E17: Research & Development | F17: 21 | G17: 4 | H17: Life Sciences | I17: 1 | J17: 20 | L17: Female | M17: 51 | N17: 4 | O17: 3 | P17: Manufacturing Director | Q17: 1 | R17: Divorced | S17: 9980 | T17: 10195 | U17: 1 | V17: Y | W17: No | X17: 11 | Y17: 3 | Z17: 3 | AA17: 80 | AB17: 1 | AC17: 10 | AD17: 1 | AE17: 3 | AF17: 10 | AG17: 9 | AH17: 8 | AI17: 8
A18: 32 | B18: No | C18: Travel_Rarely | D18: 334 | E18: Research & Development | F18: 5 | G18: 2 | H18: Life Sciences | I18: 1 | J18: 21 | K18: 1 | L18: Male | M18: 80 | N18: 4 | O18: 1 | P18: Research Scientist | Q18: 2 | R18: Divorced | S18: 3298 | T18: 15053 | U18: 0 | V18: Y | W18: Yes | X18: 12 | Y18: 3 | Z18: 4 | AA18: 80 | AB18: 2 | AC18: 7 | AD18: 5 | AE18: 2 | AF18: 6 | AG18: 2 | AH18: 0 | AI18: 5
A19: 22 | B19: No | C19: Non-Travel | D19: 1123 | E19: Research & Development | F19: 16 | G19: 2 | H19: Medical | I19: 1 | J19: 22 | K19: 4 | L19: Male | M19: 96 | N19: 4 | O19: 1 | P19: Laboratory Technician | Q19: 4 | R19: Divorced | S19: 2935 | T19: 7324 | U19: 1 | V19: Y | W19: Yes | X19: 13 | Y19: 3 | Z19: 2 | AA19: 80 | AB19: 2 | AC19: 1 | AD19: 2 | AE19: 2 | AF19: 1 | AG19: 0 | AH19: 0 | AI19: 0
A20: 53 | B20: No | C20: Travel_Rarely | D20: 1219 | E20: Sales | F20: 2 | G20: 4 | H20: Life Sciences | I20: 1 | J20: 23 | K20: 1 | L20: Female | M20: 78 | N20: 2 | O20: 4 | P20: Manager | Q20: 4 | R20: Married | S20: 15427 | T20: 22021 | U20: 2 | V20: Y | W20: No | X20: 16 | Y20: 3 | Z20: 3 | AA20: 80 | AB20: 0 | AC20: 31 | AD20: 3 | AE20: 3 | AF20: 25 | AG20: 8 | AH20: 3 | AI20: 7
A21: 38 | B21: No | C21: Travel_Rarely | D21: 371 | E21: Research & Development | F21: 2 | G21: 3 | H21: Life Sciences | I21: 1 | J21: 24 | K21: 4 | L21: Male | M21: 45 | N21: 3 | O21: 1 | P21: Research Scientist | Q21: 4 | R21: Single | S21: 3944 | T21: 4306 | U21: 5 | V21: Y | W21: Yes | X21: 11 | Y21: 3 | Z21: 3 | AA21: 80 | AB21: 0 | AC21: 6 | AD21: 3 | AE21: 3 | AF21: 3 | AG21: 2 | AH21: 1 | AI21: 2
A22: 24 | B22: No | C22: Non-Travel | D22: 673 | E22: Research & Development | F22: 11 | G22: 2 | H22: Other | I22: 1 | J22: 26 | K22: 1 | L22: Female | M22: 96 | N22: 4 | O22: 2 | P22: Manufacturing Director | Q22: 3 | R22: Divorced | S22: 4011 | T22: 8232 | U22: 0 | V22: Y | W22: No | X22: 18 | Y22: 3 | Z22: 4 | AA22: 80 | AB22: 1 | AC22: 5 | AD22: 5 | AE22: 2 | AF22: 4 | AG22: 2 | AH22: 1 | AI22: 3
A23: 36 | B23: Yes | C23: Travel_Rarely | D23: 1218 | E23: Sales | F23: 9 | G23: 4 | H23: Life Sciences | I23: 1 | J23: 27 | K23: 3 | L23: Male | M23: 82 | N23: 2 | O23: 1 | P23: Sales Representative | Q23: 1 | R23: Single | S23: 3407 | T23: 6986 | U23: 7 | V23: Y | W23: No | X23: 23 | Y23: 4 | Z23: 2 | AA23: 80 | AB23: 0 | AC23: 10 | AD23: 4 | AE23: 3 | AF23: 5 | AG23: 3 | AH23: 0 | AI23: 3
A24: 34 | B24: No | C24: Travel_Rarely | D24: 419 | E24: Research & Development | F24: 7 | G24: 4 | H24: Life Sciences | I24: 1 | J24: 28 | K24: 1 | L24: Female | M24: 53 | N24: 3 | O24: 3 | P24: Research Director | Q24: 2 | R24: Single | S24: 11994 | T24: 21293 | U24: 0 | V24: Y | W24: No | X24: 11 | Y24: 3 | Z24: 3 | AA24: 80 | AB24: 0 | AC24: 13 | AD24: 4 | AE24: 3 | AF24: 12 | AG24: 6 | AH24: 2 | AI24: 11
A25: 21 | B25: No | C25: Travel_Rarely | D25: 391 | E25: Research & Development | F25: 15 | G25: 2 | H25: Life Sciences | I25: 1 | J25: 30 | K25: 3 | L25: Male | M25: 96 | N25: 3 | O25: 1 | P25: Research Scientist | Q25: 4 | R25: Single | S25: 1232 | T25: 19281 | U25: 1 | V25: Y | W25: No | X25: 14 | Y25: 3 | Z25: 4 | AA25: 80 | AB25: 0 | AC25: 0 | AD25: 6 | AE25: 3 | AF25: 0 | AG25: 0 | AH25: 0 | AI25: 0
A26: 34 | B26: Yes | C26: Travel_Rarely | D26: 699 | E26: Research & Development | F26: 6 | G26: 1 | H26: Medical | I26: 1 | J26: 31 | K26: 2 | L26: Male | M26: 83 | N26: 3 | O26: 1 | P26: Research Scientist | Q26: 1 | R26: Single | S26: 2960 | T26: 17102 | U26: 2 | V26: Y | W26: No | X26: 11 | Y26: 3 | Z26: 3 | AA26: 80 | AB26: 0 | AC26: 8 | AD26: 2 | AE26: 3 | AF26: 4 | AG26: 2 | AH26: 1 | AI26: 3
A27: 35 years | B27: No | C27: Travel_Rarely | D27: 1282 | E27: Research & Development | F27: 5 | G27: 3 | H27: Other | I27: 1 | J27: 32 | K27: 3 | L27: Female | M27: 58 | N27: 3 | O27: 5 | P27: Manager | Q27: 3 | R27: Divorced | S27: 19094 | T27: 10735 | U27: 4 | V27: Y | W27: No | X27: 11 | Y27: 3 | Z27: 4 | AA27: 80 | AB27: 1 | AC27: 26 | AD27: 3 | AE27: 2 | AF27: 14 | AG27: 13 | AH27: 4 | AI27: 8
A28: 32 | B28: Yes | C28: Travel_Frequently | D28: 1125 | E28: Research & Development | F28: 16 | G28: 1 | H28: Life Sciences | I28: 1 | J28: 33 | K28: 2 | L28: Female | M28: 72 | N28: 1 | O28: 1 | P28: Research Scientist | Q28: 1 | R28: Single | S28: 3919 | T28: 4681 | U28: 1 | V28: Y | W28: Yes | X28: 22 | Y28: 4 | Z28: 2 | AA28: 80 | AB28: 0 | AC28: 10 | AD28: 5 | AE28: 3 | AF28: 10 | AG28: 2 | AH28: 6 | AI28: 7
A29: 42 | B29: No | C29: Travel_Rarely | D29: 691 | E29: Sales | F29: 8 | G29: 4 | H29: Marketing | I29: 1 | J29: 35 | K29: 3 | L29: Male | M29: 48 | N29: 3 | O29: 2 | P29: Sales Executive | Q29: 2 | R29: Married | S29: 6825 | T29: 21173 | U29: 0 | V29: Y | W29: No | X29: 11 | Y29: 3 | Z29: 4 | AA29: 80 | AB29: 1 | AC29: 10 | AD29: 2 | AE29: 3 | AF29: 9 | AG29: 7 | AH29: 4 | AI29: 2
A30: 44 | B30: No | C30: Travel_Rarely | D30: 477 | E30: Research & Development | F30: 7 | G30: 4 | H30: Medical | I30: 1 | J30: 36 | K30: 1 | L30: Female | M30: 42 | N30: 2 | O30: 3 | P30: Healthcare Representative | Q30: 4 | R30: Married | S30: 10248 | T30: 2094 | U30: 3 | V30: Y | W30: No | X30: 14 | Y30: 3 | Z30: 4 | AA30: 80 | AB30: 1 | AC30: 24 | AD30: 4 | AE30: 3 | AF30: 22 | AG30: 6 | AH30: 5 | AI30: 17
A31: 46 | B31: No | C31: Travel_Rarely | D31: 705 | E31: Sales | F31: 2 | G31: 4 | H31: Marketing | I31: 1 | J31: 38 | K31: 2 | L31: Female | M31: 83 | N31: 3 | O31: 5 | P31: Manager | Q31: 1 | R31: Single | S31: 18947 | T31: 22822 | U31: 3 | V31: Y | W31: No | X31: 12 | Y31: 3 | Z31: 4 | AA31: 80 | AB31: 0 | AC31: 22 | AD31: 2 | AE31: 2 | AF31: 2 | AG31: 2 | AH31: 2 | AI31: 1
A32: 33 | B32: No | C32: Travel_Rarely | D32: 924 | E32: Research & Development | F32: 2 | G32: 3 | H32: Medical | I32: 1 | J32: 39 | K32: 3 | L32: Male | M32: 78 | N32: 3 | O32: 1 | P32: Laboratory Technician | Q32: 4 | R32: Single | S32: 2496 | T32: 6670 | U32: 4 | V32: Y | W32: No | X32: 11 | Y32: 3 | Z32: 4 | AA32: 80 | AB32: 0 | AC32: 7 | AD32: 3 | AE32: 3 | AF32: 1 | AG32: 1 | AH32: 0 | AI32: 0
A33: 44 | B33: No | C33: Travel_Rarely | D33: 1459 | E33: Research & Development | F33: 10 | G33: 4 | H33: Other | I33: 1 | J33: 40 | K33: 4 | L33: Male | M33: 41 | N33: 3 | O33: 2 | P33: Healthcare Representative | Q33: 4 | R33: Married | S33: 6465 | T33: 19121 | U33: 2 | V33: Y | W33: Yes | X33: 13 | Y33: 3 | Z33: 4 | AA33: 80 | AB33: 0 | AC33: 9 | AD33: 5 | AE33: 4 | AF33: 4 | AG33: 2 | AH33: 1 | AI33: 3
A34: 30 | B34: No | C34: Travel_Rarely | D34: 125 | E34: Research & Development | F34: 9 | G34: 2 | H34: Medical | I34: 1 | J34: 41 | K34: 4 | L34: Male | M34: 83 | N34: 2 | O34: 1 | P34: Laboratory Technician | Q34: 3 | R34: Single | S34: 2206 | T34: 16117 | U34: 1 | V34: Y | W34: No | X34: 13 | Y34: 3 | Z34: 1 | AA34: 80 | AB34: 0 | AC34: 10 | AD34: 5 | AE34: 3 | AF34: 10 | AG34: 0 | AH34: 1 | AI34: 8
A35: 39 | B35: Yes | C35: Travel_Rarely | D35: 895 | E35: Sales | F35: 5 | G35: 3 | H35: Technical Degree | I35: 1 | J35: 42 | K35: 4 | L35: Male | M35: 56 | N35: 3 | O35: 2 | P35: Sales Representative | Q35: 4 | R35: Married | S35: 2086 | T35: 3335 | U35: 3 | V35: Y | W35: No | X35: 14 | Y35: 3 | Z35: 3 | AA35: 80 | AB35: 1 | AC35: 19 | AD35: 6 | AE35: 4 | AF35: 1 | AG35: 0 | AH35: 0 | AI35: 0
A36: 24 | B36: Yes | C36: Travel_Rarely | D36: 813 | E36: Research & Development | F36: 1 | G36: 3 | H36: Medical | I36: 1 | J36: 45 | K36: 2 | L36: Male | M36: 61 | N36: 3 | O36: 1 | P36: Research Scientist | Q36: 4 | R36: Married | S36: 2293 | T36: 3020 | U36: 2 | V36: Y | W36: Yes | X36: 16 | Y36: 3 | Z36: 1 | AA36: 80 | AB36: 1 | AC36: 6 | AD36: 2 | AE36: 2 | AF36: 2 | AG36: 0 | AH36: 2 | AI36: 0
A37: 29 yrs | B37: No | C37: Travel_Rarely | D37: 1273 | E37: Research & Development | F37: 2 | G37: 2 | H37: Medical | I37: 1 | J37: 46 | K37: 4 | L37: Female | M37: 72 | N37: 4 | O37: 1 | P37: Research Scientist | Q37: 3 | R37: Divorced | S37: 2645 | T37: 21923 | U37: 1 | V37: Y | W37: No | X37: 12 | Y37: 3 | Z37: 4 | AA37: 80 | AB37: 2 | AC37: 6 | AD37: 3 | AE37: 2 | AF37: 5 | AG37: 3 | AH37: 1 | AI37: 4
A38: 50 | B38: Yes | C38: Travel_Rarely | D38: 869 | E38: Sales | F38: 3 | G38: 2 | H38: Marketing | I38: 1 | J38: 47 | K38: 1 | L38: Male | M38: 86 | N38: 2 | O38: 1 | P38: Sales Representative | Q38: 3 | R38: Married | S38: 2683 | T38: 3810 | U38: 1 | V38: Y | W38: Yes | X38: 14 | Y38: 3 | Z38: 3 | AA38: 80 | AB38: 0 | AC38: 3 | AD38: 2 | AE38: 3 | AF38: 3 | AG38: 2 | AH38: 0 | AI38: 2
A39: 35 | B39: No | C39: Travel_Rarely | D39: 890 | E39: Sales | F39: 2 | G39: 3 | H39: Marketing | I39: 1 | J39: 49 | K39: 4 | L39: Female | M39: 97 | N39: 3 | O39: 1 | P39: Sales Representative | Q39: 4 | R39: Married | S39: 2014 | T39: 9687 | U39: 1 | V39: Y | W39: No | X39: 13 | Y39: 3 | Z39: 1 | AA39: 80 | AB39: 0 | AC39: 2 | AD39: 3 | AE39: 3 | AF39: 2 | AG39: 2 | AH39: 2 | AI39: 2
A40: 36 | B40: No | C40: Travel_Rarely | D40: 852 | E40: Research & Development | F40: 5 | G40: 4 | H40: Life Sciences | I40: 1 | J40: 51 | K40: 2 | L40: Female | M40: 82 | N40: 2 | O40: 1 | P40: Research Scientist | Q40: 1 | R40: Married | S40: 3419 | T40: 13072 | U40: 9 | V40: Y | W40: Yes | X40: 14 | Y40: 3 | Z40: 4 | AA40: 80 | AB40: 1 | AC40: 6 | AD40: 3 | AE40: 4 | AF40: 1 | AG40: 1 | AH40: 0 | AI40: 0
A41: 33 | B41: No | C41: Travel_Frequently | D41: 1141 | E41: Sales | F41: 1 | G41: 3 | H41: Life Sciences | I41: 1 | J41: 52 | K41: 3 | L41: Female | M41: 42 | N41: 4 | O41: 2 | P41: Sales Executive | Q41: 1 | R41: Married | S41: 5376 | T41: 3193 | U41: 2 | V41: Y | W41: No | X41: 19 | Y41: 3 | Z41: 1 | AA41: 80 | AB41: 2 | AC41: 10 | AD41: 3 | AE41: 3 | AF41: 5 | AG41: 3 | AH41: 1 | AI41: 3
A42: 35 | B42: No | C42: Travel_Rarely | D42: 464 | E42: Research & Development | F42: 4 | G42: 2 | H42: Other | I42: 1 | J42: 53 | K42: 3 | L42: Male | M42: 75 | N42: 3 | O42: 1 | P42: Laboratory Technician | Q42: 4 | R42: Divorced | S42: 1951 | T42: 10910 | U42: 1 | V42: Y | W42: No | X42: 12 | Y42: 3 | Z42: 3 | AA42: 80 | AB42: 1 | AC42: 1 | AD42: 3 | AE42: 3 | AF42: 1 | AG42: 0 | AH42: 0 | AI42: 0
A43: 27 | B43: No | C43: Travel_Rarely | D43: 1240 | E43: Research & Development | F43: 2 | G43: 4 | H43: Life Sciences | I43: 1 | J43: 54 | K43: 4 | L43: Female | M43: 33 | N43: 3 | O43: 1 | P43: Laboratory Technician | Q43: 1 | R43: Divorced | S43: 2341 | T43: 19715 | U43: 1 | V43: Y | W43: No | X43: 13 | Y43: 3 | Z43: 4 | AA43: 80 | AB43: 1 | AC43: 1 | AD43: 6 | AE43: 3 | AF43: 1 | AG43: 0 | AH43: 0 | AI43: 0
A44: 26 | B44: Yes | C44: Travel_Rarely | D44: 1357 | E44: Research & Development | F44: 25 | G44: 3 | H44: Life Sciences | I44: 1 | J44: 55 | K44: 1 | L44: Male | M44: 48 | N44: 1 | O44: 1 | P44: Laboratory Technician | Q44: 3 | R44: Single | S44: 2293 | T44: 10558 | U44: 1 | V44: Y | W44: No | X44: 12 | Y44: 3 | Z44: 3 | AA44: 80 | AB44: 0 | AC44: 1 | AD44: 2 | AE44: 2 | AF44: 1 | AG44: 0 | AH44: 0 | AI44: 1
A45: 27 | B45: No | C45: Travel_Frequently | D45: 994 | E45: Sales | F45: 8 | G45: 3 | H45: Life Sciences | I45: 1 | J45: 56 | K45: 4 | L45: Male | M45: 37 | N45: 3 | O45: 3 | P45: Sales Executive | Q45: 3 | R45: Single | S45: 8726 | T45: 2975 | U45: 1 | V45: Y | W45: No | X45: 15 | Y45: 3 | Z45: 4 | AA45: 80 | AB45: 0 | AC45: 9 | AD45: 0 | AE45: 3 | AF45: 9 | AG45: 8 | AH45: 1 | AI45: 7
A46: 30 | B46: No | C46: Travel_Frequently | D46: 721 | E46: Research & Development | F46: 1 | G46: 2 | H46: Medical | I46: 1 | J46: 57 | K46: 3 | L46: Female | M46: 58 | N46: 3 | O46: 2 | P46: Laboratory Technician | Q46: 4 | R46: Single | S46: 4011 | T46: 10781 | U46: 1 | V46: Y | W46: No | X46: 23 | Y46: 4 | Z46: 4 | AA46: 80 | AB46: 0 | AC46: 12 | AD46: 2 | AE46: 3 | AF46: 12 | AG46: 8 | AH46: 3 | AI46: 7
A47: 44 years | B47: Yes | C47: Travel_Rarely | D47: 1360 | E47: Research & Development | F47: 12 | G47: 3 | H47: Technical Degree | I47: 1 | J47: 58 | K47: 2 | L47: Female | M47: 49 | N47: 3 | O47: 5 | P47: Research Director | Q47: 3 | R47: Married | S47: 19545 | T47: 16280 | U47: 1 | V47: Y | W47: No | X47: 12 | Y47: 3 | Z47: 4 | AA47: 80 | AB47: 0 | AC47: 23 | AD47: 0 | AE47: 3 | AF47: 22 | AG47: 15 | AH47: 15 | AI47: 8
A48: 34 | B48: No | C48: Non-Travel | D48: 1065 | E48: Sales | F48: 23 | G48: 4 | H48: Marketing | I48: 1 | J48: 60 | K48: 2 | L48: Male | M48: 72 | N48: 3 | O48: 2 | P48: Sales Executive | Q48: 3 | R48: Single | S48: 4568 | T48: 10034 | U48: 0 | V48: Y | W48: No | X48: 20 | Y48: 4 | Z48: 3 | AA48: 80 | AB48: 0 | AC48: 10 | AD48: 2 | AE48: 3 | AF48: 9 | AG48: 5 | AH48: 8 | AI48: 7
A49: 37 | B49: No | C49: Travel_Rarely | D49: 408 | E49: Research & Development | F49: 19 | G49: 2 | H49: Life Sciences | I49: 1 | J49: 61 | K49: 2 | L49: Male | M49: 73 | N49: 3 | O49: 1 | P49: Research Scientist | Q49: 2 | R49: Married | S49: 3022 | T49: 10227 | U49: 4 | V49: Y | W49: No | X49: 21 | Y49: 4 | Z49: 1 | AA49: 80 | AB49: 0 | AC49: 8 | AD49: 1 | AE49: 3 | AF49: 1 | AG49: 0 | AH49: 0 | AI49: 0
A50: 46 | B50: No | C50: Travel_Frequently | D50: 1211 | E50: Sales | F50: 5 | G50: 4 | H50: Marketing | I50: 1 | J50: 62 | K50: 1 | L50: Male | M50: 98 | N50: 3 | O50: 2 | P50: Sales Executive | Q50: 4 | R50: Single | S50: 5772 | T50: 20445 | U50: 4 | V50: Y | W50: Yes | X50: 21 | Y50: 4 | Z50: 3 | AA50: 80 | AB50: 0 | AC50: 14 | AD50: 4 | AE50: 3 | AF50: 9 | AG50: 6 | AH50: 0 | AI50: 8
A51: 35 | B51: No | C51: Travel_Rarely | D51: 1229 | E51: Research & Development | F51: 8 | G51: 1 | H51: Life Sciences | I51: 1 | J51: 63 | K51: 4 | L51: Male | M51: 36 | N51: 4 | O51: 1 | P51: Laboratory Technician | Q51: 4 | R51: Married | S51: 2269 | T51: 4892 | U51: 1 | V51: Y | W51: No | X51: 19 | Y51: 3 | Z51: 4 | AA51: 80 | AB51: 0 | AC51: 1 | AD51: 2 | AE51: 3 | AF51: 1 | AG51: 0 | AH51: 0 | AI51: 1
A52: 48 | B52: Yes | C52: Travel_Rarely | D52: 626 | F52: 1 | G52: 2 | H52: Life Sciences | I52: 1 | J52: 64 | K52: 1 | L52: Male | M52: 98 | N52: 2 | O52: 3 | P52: Laboratory Technician | Q52: 3 | R52: Single | S52: 5381 | T52: 19294 | U52: 9 | V52: Y | W52: Yes | X52: 13 | Y52: 3 | Z52: 4 | AA52: 80 | AB52: 0 | AC52: 23 | AD52: 2 | AE52: 3 | AF52: 1 | AG52: 0 | AH52: 0 | AI52: 0
A53: 28 | B53: Yes | C53: Travel_Rarely | D53: 1434 | E53: Research & Development | F53: 5 | G53: 4 | H53: Technical Degree | I53: 1 | J53: 65 | K53: 3 | L53: Male | M53: 50 | N53: 3 | O53: 1 | P53: Laboratory Technician | Q53: 3 | R53: Single | S53: 3441 | T53: 11179 | U53: 1 | V53: Y | W53: Yes | X53: 13 | Y53: 3 | Z53: 3 | AA53: 80 | AB53: 0 | AC53: 2 | AD53: 3 | AE53: 2 | AF53: 2 | AG53: 2 | AH53: 2 | AI53: 2
A54: 44 | B54: No | C54: Travel_Rarely | D54: 1488 | E54: Sales | F54: 1 | G54: 5 | H54: Marketing | I54: 1 | J54: 68 | K54: 2 | L54: Female | M54: 75 | N54: 3 | O54: 2 | P54: Sales Executive | Q54: 1 | R54: Divorced | S54: 5454 | T54: 4009 | U54: 5 | V54: Y | W54: Yes | X54: 21 | Y54: 4 | Z54: 3 | AA54: 80 | AB54: 1 | AC54: 9 | AD54: 2 | AE54: 2 | AF54: 4 | AG54: 3 | AH54: 1 | AI54: 3
A55: 35 | B55: No | C55: Non-Travel | D55: 1097 | E55: Research & Development | F55: 11 | G55: 2 | H55: Medical | I55: 1 | J55: 70 | K55: 3 | L55: Male | M55: 79 | N55: 2 | O55: 3 | P55: Healthcare Representative | Q55: 1 | R55: Married | S55: 9884 | T55: 8302 | U55: 2 | V55: Y | W55: Yes | X55: 13 | Y55: 3 | Z55: 3 | AA55: 80 | AB55: 1 | AC55: 10 | AD55: 3 | AE55: 3 | AF55: 4 | AG55: 0 | AH55: 2 | AI55: 3
A56: 26 | B56: No | C56: Travel_Rarely | D56: 1443 | E56: Sales | F56: 23 | G56: 3 | H56: Marketing | I56: 1 | J56: 72 | K56: 3 | L56: Female | M56: 47 | N56: 2 | O56: 2 | P56: Sales Executive | Q56: 4 | R56: Married | S56: 4157 | T56: 21436 | U56: 7 | V56: Y | W56: Yes | X56: 19 | Y56: 3 | Z56: 3 | AA56: 80 | AB56: 1 | AC56: 5 | AD56: 2 | AE56: 2 | AF56: 2 | AG56: 2 | AH56: 0 | AI56: 0
A57: 33 | B57: No | C57: Travel_Frequently | D57: 515 | E57: Research & Development | F57: 1 | G57: 2 | H57: Life Sciences | I57: 1 | J57: 73 | K57: 1 | L57: Female | M57: 98 | N57: 3 | O57: 3 | P57: Research Director | Q57: 4 | R57: Single | S57: 5993 | T57: 15146 | U57: 1 | V57: Y | W57: Yes | X57: 12 | Y57: 3 | Z57: 3 | AA57: 80 | AB57: 0 | AC57: 15 | AD57: 1 | AE57: 3 | AF57: 15 | AG57: 14 | AH57: 8 | AI57: 12
A58: 35 | B58: No | C58: Travel_Frequently | D58: 853 | E58: Sales | F58: 18 | G58: 5 | H58: Life Sciences | I58: 1 | J58: 74 | K58: 2 | L58: Male | M58: 71 | N58: 3 | O58: 3 | P58: Sales Executive | Q58: 1 | R58: Married | S58: 9069 | T58: 11031 | U58: 1 | V58: Y | W58: No | X58: 22 | Y58: 4 | Z58: 4 | AA58: 80 | AB58: 1 | AC58: 9 | AD58: 3 | AE58: 2 | AF58: 9 | AG58: 8 | AH58: 1 | AI58: 8
A59: 35 | B59: No | C59: Travel_Rarely | D59: 1142 | E59: Research & Development | F59: 23 | G59: 4 | H59: Medical | I59: 1 | J59: 75 | K59: 3 | L59: Female | M59: 30 | N59: 3 | O59: 1 | P59: Laboratory Technician | Q59: 1 | R59: Married | S59: 4014 | T59: 16002 | U59: 3 | V59: Y | W59: Yes | X59: 15 | Y59: 3 | Z59: 3 | AA59: 80 | AB59: 1 | AC59: 4 | AD59: 3 | AE59: 3 | AF59: 2 | AG59: 2 | AH59: 2 | AI59: 2
A60: 31 | B60: No | C60: Travel_Rarely | D60: 655 | E60: Research & Development | F60: 7 | G60: 4 | H60: Life Sciences | I60: 1 | J60: 76 | K60: 4 | L60: Male | M60: 48 | N60: 3 | O60: 2 | P60: Laboratory Technician | Q60: 4 | R60: Divorced | S60: 5915 | T60: 9528 | U60: 3 | V60: Y | W60: No | X60: 22 | Y60: 4 | Z60: 4 | AA60: 80 | AB60: 1 | AC60: 10 | AD60: 3 | AE60: 2 | AF60: 7 | AG60: 7 | AH60: 1 | AI60: 7
A61: 37 | B61: No | C61: Travel_Rarely | D61: 1115 | E61: Research & Development | F61: 1 | G61: 4 | H61: Life Sciences | I61: 1 | J61: 77 | K61: 1 | L61: Male | M61: 51 | N61: 2 | O61: 2 | P61: Manufacturing Director | Q61: 3 | R61: Divorced | S61: 5993 | T61: 2689 | U61: 1 | V61: Y | W61: No | X61: 18 | Y61: 3 | Z61: 3 | AA61: 80 | AB61: 1 | AC61: 7 | AD61: 2 | AE61: 4 | AF61: 7 | AG61: 5 | AH61: 0 | AI61: 7
A62: 32 | B62: No | C62: Travel_Rarely | D62: 427 | E62: Research & Development | F62: 1 | G62: 3 | H62: Medical | I62: 1 | J62: 78 | K62: 1 | L62: Male | M62: 33 | N62: 3 | O62: 2 | P62: Manufacturing Director | Q62: 4 | R62: Married | S62: 6162 | T62: 10877 | U62: 1 | V62: Y | W62: Yes | X62: 22 | Y62: 4 | Z62: 2 | AA62: 80 | AB62: 1 | AD62: 3 | AE62: 3 | AF62: 9 | AG62: 8 | AH62: 7 | AI62: 8
A63: 38 | B63: No | C63: Travel_Frequently | D63: 653 | E63: Research & Development | F63: 29 | G63: 5 | H63: Life Sciences | I63: 1 | J63: 79 | K63: 4 | L63: Female | M63: 50 | N63: 3 | O63: 2 | P63: Laboratory Technician | Q63: 4 | R63: Single | S63: 2406 | T63: 5456 | U63: 1 | V63: Y | W63: No | X63: 11 | Y63: 3 | Z63: 4 | AA63: 80 | AB63: 0 | AC63: 10 | AD63: 2 | AE63: 3 | AF63: 10 | AG63: 3 | AH63: 9 | AI63: 9
A64: 50 | B64: No | C64: Travel_Rarely | D64: 989 | E64: Research & Development | F64: 7 | G64: 2 | H64: Medical | I64: 1 | J64: 80 | K64: 2 | L64: Female | M64: 43 | N64: 2 | O64: 5 | P64: Research Director | Q64: 3 | R64: Divorced | S64: 18740 | T64: 16701 | U64: 5 | V64: Y | W64: Yes | X64: 12 | Y64: 3 | Z64: 4 | AA64: 80 | AB64: 1 | AC64: 29 | AD64: 2 | AE64: 2 | AF64: 27 | AG64: 3 | AH64: 13 | AI64: 8
A65: 59 | B65: No | C65: Travel_Rarely | D65: 1435 | E65: Sales | F65: 25 | G65: 3 | H65: Life Sciences | I65: 1 | J65: 81 | K65: 1 | L65: Female | M65: 99 | N65: 3 | O65: 3 | P65: Sales Executive | Q65: 1 | R65: Single | S65: 7637 | T65: 2354 | U65: 7 | V65: Y | W65: No | X65: 11 | Y65: 3 | Z65: 4 | AA65: 80 | AB65: 0 | AC65: 28 | AD65: 3 | AE65: 2 | AF65: 21 | AG65: 16 | AH65: 7 | AI65: 9
A66: 36 | B66: No | C66: Travel_Rarely | D66: 1223 | E66: Research & Development | F66: 8 | G66: 3 | H66: Technical Degree | I66: 1 | J66: 83 | K66: 3 | L66: Female | M66: 59 | N66: 3 | O66: 3 | P66: Healthcare Representative | Q66: 3 | R66: Divorced | S66: 10096 | T66: 8202 | U66: 1 | V66: Y | W66: No | X66: 13 | Y66: 3 | Z66: 2 | AA66: 80 | AB66: 3 | AC66: 17 | AD66: 2 | AE66: 3 | AF66: 17 | AG66: 14 | AH66: 12 | AI66: 8
A67: 55 | B67: No | C67: Travel_Rarely | D67: 836 | E67: Research & Development | F67: 8 | G67: 3 | H67: Medical | I67: 1 | J67: 84 | K67: 4 | L67: Female | M67: 33 | N67: 3 | O67: 4 | P67: Manager | Q67: 3 | R67: Divorced | S67: 4200 | T67: 19730 | U67: 2 | V67: Y | W67: Yes | X67: 14 | Y67: 3 | Z67: 3 | AA67: 80 | AB67: 3 | AC67: 21 | AD67: 2 | AE67: 3 | AF67: 5 | AG67: 0 | AH67: 0 | AI67: 2
A68: 36 | B68: No | C68: Travel_Frequently | D68: 1195 | E68: Research & Development | F68: 11 | G68: 3 | H68: Life Sciences | I68: 1 | J68: 85 | K68: 2 | L68: Male | M68: 95 | N68: 2 | O68: 2 | P68: Manufacturing Director | Q68: 2 | R68: Single | S68: 6499 | T68: 22656 | U68: 1 | V68: Y | W68: No | X68: 13 | Y68: 3 | Z68: 3 | AA68: 80 | AB68: 0 | AC68: 6 | AD68: 3 | AE68: 3 | AF68: 6 | AG68: 5 | AH68: 0 | AI68: 3
A69: 45 | B69: No | C69: Travel_Rarely | D69: 1339 | E69: Research & Development | F69: 7 | G69: 3 | H69: Life Sciences | I69: 1 | J69: 86 | K69: 2 | L69: Male | M69: 59 | N69: 3 | O69: 3 | P69: Research Scientist | Q69: 1 | R69: Divorced | S69: 9724 | T69: 18787 | U69: 2 | V69: Y | W69: No | X69: 17 | Y69: 3 | Z69: 3 | AA69: 80 | AB69: 1 | AC69: 25 | AD69: 2 | AE69: 3 | AF69: 1 | AG69: 0 | AH69: 0 | AI69: 0
A70: 35 | B70: No | C70: Travel_Frequently | D70: 664 | E70: Research & Development | F70: 1 | G70: 3 | H70: Medical | I70: 1 | J70: 88 | K70: 2 | L70: Male | M70: 79 | N70: 3 | O70: 1 | P70: Research Scientist | Q70: 1 | R70: Married | S70: 2194 | T70: 5868 | U70: 4 | V70: Y | W70: No | X70: 13 | Y70: 3 | Z70: 4 | AA70: 80 | AB70: 1 | AC70: 5 | AD70: 2 | AE70: 2 | AF70: 3 | AG70: 2 | AH70: 1 | AI70: 2
A71: 36 | B71: Yes | C71: Travel_Rarely | D71: 318 | E71: Research & Development | F71: 9 | G71: 3 | H71: Medical | I71: 1 | J71: 90 | K71: 4 | L71: Male | M71: 79 | N71: 2 | O71: 1 | P71: Research Scientist | Q71: 3 | R71: Married | S71: 3388 | T71: 21777 | U71: 0 | V71: Y | W71: Yes | X71: 17 | Y71: 3 | Z71: 1 | AA71: 80 | AB71: 1 | AC71: 2 | AD71: 0 | AE71: 2 | AF71: 1 | AG71: 0 | AH71: 0 | AI71: 0
A72: 59 | B72: No | D72: 1225 | E72: Sales | F72: 1 | G72: 1 | H72: Life Sciences | I72: 1 | J72: 91 | K72: 1 | L72: Female | M72: 57 | N72: 2 | O72: 2 | P72: Sales Executive | Q72: 3 | R72: Single | S72: 5473 | T72: 24668 | U72: 7 | V72: Y | W72: No | X72: 11 | Y72: 3 | Z72: 4 | AA72: 80 | AB72: 0 | AC72: 20 | AD72: 2 | AE72: 2 | AF72: 4 | AG72: 3 | AH72: 1 | AI72: 3
A73: 29 | B73: No | C73: Travel_Rarely | D73: 1328 | E73: Research & Development | F73: 2 | G73: 3 | H73: Life Sciences | I73: 1 | J73: 94 | K73: 3 | L73: Male | M73: 76 | N73: 3 | O73: 1 | P73: Research Scientist | Q73: 2 | R73: Married | S73: 2703 | T73: 4956 | U73: 0 | V73: Y | W73: No | X73: 23 | Y73: 4 | Z73: 4 | AA73: 80 | AB73: 1 | AC73: 6 | AD73: 3 | AE73: 3 | AF73: 5 | AG73: 4 | AH73: 0 | AI73: 4
A74: 31 | B74: No | C74: Travel_Rarely | D74: 1082 | E74: Research & Development | F74: 1 | G74: 4 | H74: Medical | I74: 1 | J74: 95 | K74: 3 | L74: Male | M74: 87 | N74: 3 | O74: 1 | P74: Research Scientist | Q74: 2 | R74: Single | S74: 2501 | T74: 18775 | U74: 1 | V74: Y | W74: No | X74: 17 | Y74: 3 | Z74: 2 | AA74: 80 | AB74: 0 | AC74: 1 | AD74: 4 | AE74: 3 | AF74: 1 | AG74: 1 | AH74: 1 | AI74: 0
A75: 32 | B75: No | C75: Travel_Rarely | D75: 548 | E75: Research & Development | F75: 1 | G75: 3 | H75: Life Sciences | I75: 1 | J75: 96 | K75: 2 | L75: Male | M75: 66 | N75: 3 | O75: 2 | P75: Research Scientist | Q75: 2 | R75: Married | S75: 6220 | T75: 7346 | U75: 1 | V75: Y | W75: No | X75: 17 | Y75: 3 | Z75: 2 | AA75: 80 | AB75: 2 | AC75: 10 | AD75: 3 | AE75: 3 | AF75: 10 | AG75: 4 | AH75: 0 | AI75: 9
A76: 36 | B76: No | C76: Travel_Rarely | D76: 132 | E76: Research & Development | F76: 6 | G76: 3 | H76: Life Sciences | I76: 1 | J76: 97 | K76: 2 | L76: Female | M76: 55 | N76: 4 | O76: 1 | P76: Laboratory Technician | Q76: 4 | R76: Married | S76: 3038 | T76: 22002 | U76: 3 | V76: Y | W76: No | X76: 12 | Y76: 3 | Z76: 2 | AA76: 80 | AB76: 0 | AC76: 5 | AD76: 3 | AE76: 3 | AF76: 1 | AG76: 0 | AH76: 0 | AI76: 0
A77: 31 | B77: No | C77: Travel_Rarely | D77: 746 | E77: Research & Development | F77: 8 | G77: 4 | H77: Life Sciences | I77: 1 | J77: 98 | K77: 3 | L77: Female | M77: 61 | N77: 3 | O77: 2 | P77: Manufacturing Director | Q77: 4 | R77: Single | S77: 6500 USD | T77: 20682 | U77: 1 | V77: Y | W77: No | X77: 23 | Y77: 4 | Z77: 4 | AA77: 80 | AB77: 0 | AC77: 11 | AD77: 2 | AE77: 3 | AF77: 11 | AG77: 7 | AH77: 1 | AI77: 8
A78: 35 | B78: No | C78: Travel_Rarely | D78: 776 | E78: Sales | F78: 1 | G78: 4 | H78: Marketing | I78: 1 | J78: 100 | K78: 3 | L78: Male | M78: 32 | N78: 2 | O78: 2 | P78: Sales Executive | Q78: 1 | R78: Single | S78: 4312 | T78: 23016 | U78: 0 | V78: Y | W78: No | X78: 14 | Y78: 3 | Z78: 2 | AA78: 80 | AB78: 0 | AC78: 16 | AD78: 2 | AE78: 3 | AF78: 15 | AG78: 13 | AH78: 2 | AI78: 8
A79: 45 | B79: No | C79: Travel_Rarely | D79: 193 | E79: Research & Development | F79: 6 | G79: 4 | H79: Other | I79: 1 | J79: 101 | K79: 4 | L79: Male | M79: 52 | N79: 3 | O79: 3 | P79: Research Director | Q79: 1 | R79: Married | S79: 13245 | T79: 15067 | U79: 4 | V79: Y | W79: Yes | X79: 14 | Y79: 3 | Z79: 2 | AA79: 80 | AB79: 0 | AC79: 17 | AD79: 3 | AE79: 4 | AF79: 0 | AG79: 0 | AH79: 0 | AI79: 0
A80: 37 | B80: No | C80: Travel_Rarely | D80: 397 | E80: Research & Development | F80: 7 | G80: 4 | H80: Medical | I80: 1 | J80: 102 | K80: 1 | L80: Male | M80: 30 | N80: 3 | O80: 3 | P80: Research Director | Q80: 3 | R80: Single | S80: 13664 | T80: 25258 | U80: 4 | V80: Y | W80: No | X80: 13 | Y80: 3 | Z80: 1 | AA80: 80 | AB80: 0 | AC80: 16 | AD80: 3 | AE80: 4 | AF80: 5 | AG80: 2 | AH80: 0 | AI80: 2
A81: 46 | B81: No | C81: Travel_Rarely | D81: 945 | E81: Human Resources | F81: 5 | G81: 2 | H81: Medical | I81: 1 | J81: 103 | K81: 2 | L81: Male | M81: 80 | N81: 3 | O81: 2 | P81: Human Resources | Q81: 2 | R81: Divorced | S81: 5021 | T81: 10425 | U81: 8 | V81: Y | W81: Yes | X81: 22 | Y81: 4 | Z81: 4 | AA81: 80 | AB81: 1 | AC81: 16 | AD81: 2 | AE81: 3 | AF81: 4 | AG81: 2 | AH81: 0 | AI81: 2
A82: 30 | B82: No | C82: Travel_Rarely | D82: 852 | E82: Research & Development | F82: 1 | G82: 1 | H82: Life Sciences | I82: 1 | J82: 104 | K82: 4 | L82: Male | M82: 55 | N82: 2 | O82: 2 | P82: Laboratory Technician | Q82: 4 | R82: Married | S82: 5126 | T82: 15998 | U82: 1 | V82: Y | W82: Yes | X82: 12 | Y82: 3 | Z82: 3 | AA82: 80 | AB82: 2 | AC82: 10 | AD82: 1 | AE82: 2 | AF82: 10 | AG82: 8 | AH82: 3 | AI82: 0
A83: 35 | B83: No | C83: Travel_Rarely | D83: 1214 | E83: Research & Development | F83: 1 | G83: 3 | H83: Medical | I83: 1 | J83: 105 | K83: 2 | L83: Male | M83: 30 | N83: 2 | O83: 1 | P83: Research Scientist | Q83: 3 | R83: Single | S83: 2859 | T83: 26278 | U83: 1 | V83: Y | W83: No | X83: 18 | Y83: 3 | Z83: 1 | AA83: 80 | AB83: 0 | AC83: 6 | AD83: 3 | AE83: 3 | AF83: 6 | AG83: 4 | AH83: 0 | AI83: 4
A84: 55 | B84: No | C84: Travel_Rarely | D84: 111 | E84: Sales | F84: 1 | G84: 2 | H84: Life Sciences | I84: 1 | J84: 106 | K84: 1 | L84: Male | M84: 70 | N84: 3 | O84: 3 | P84: Sales Executive | Q84: 4 | R84: Married | S84: 10239 | T84: 18092 | U84: 3 | V84: Y | W84: No | X84: 14 | Y84: 3 | Z84: 4 | AA84: 80 | AB84: 1 | AC84: 24 | AD84: 4 | AE84: 3 | AF84: 1 | AG84: 0 | AH84: 1 | AI84: 0
A85: 38 | B85: No | C85: Non-Travel | D85: 573 | E85: Research & Development | F85: 6 | G85: 3 | H85: Medical | I85: 1 | J85: 107 | K85: 2 | L85: Female | M85: 79 | N85: 1 | O85: 2 | P85: Research Scientist | Q85: 4 | R85: Divorced | S85: 5329 | T85: 15717 | U85: 7 | V85: Y | W85: Yes | X85: 12 | Y85: 3 | Z85: 4 | AA85: 80 | AB85: 3 | AC85: 17 | AD85: 3 | AE85: 3 | AF85: 13 | AG85: 11 | AH85: 1 | AI85: 9
A86: 34 | B86: No | C86: Travel_Rarely | D86: 1153 | E86: Research & Development | F86: 1 | G86: 2 | H86: Medical | I86: 1 | J86: 110 | K86: 1 | L86: Male | M86: 94 | N86: 3 | O86: 2 | P86: Manufacturing Director | Q86: 2 | R86: Married | S86: 4325 | T86: 17736 | U86: 1 | V86: Y | W86: No | X86: 15 | Y86: 3 | Z86: 3 | AA86: 80 | AB86: 0 | AC86: 5 | AD86: 2 | AE86: 3 | AF86: 5 | AG86: 2 | AH86: 1 | AI86: 3
A87: 56 | B87: No | C87: Travel_Rarely | D87: 1400 | E87: Research & Development | F87: 5 miles | G87: 3 | H87: Life Sciences | I87: 1 | J87: 112 | K87: 4 | L87: Male | M87: 49 | N87: 1 | O87: 3 | P87: Manufacturing Director | Q87: 4 | R87: Single | S87: 7260 | T87: 21698 | U87: 4 | V87: Y | W87: No | X87: 11 | Y87: 3 | Z87: 1 | AA87: 80 | AB87: 0 | AC87: 37 | AD87: 3 | AE87: 2 | AF87: 6 | AG87: 4 | AH87: 0 | AI87: 2
A88: 23 | B88: No | C88: Travel_Rarely | D88: 541 | E88: Sales | F88: 2 | G88: 1 | H88: Technical Degree | I88: 1 | J88: 113 | K88: 3 | L88: Male | M88: 62 | N88: 3 | O88: 1 | P88: Sales Representative | Q88: 1 | R88: Divorced | S88: 2322 | T88: 9518 | U88: 3 | V88: Y | W88: No | X88: 13 | Y88: 3 | Z88: 3 | AA88: 80 | AB88: 1 | AC88: 3 | AD88: 3 | AE88: 3 | AF88: 0 | AG88: 0 | AH88: 0 | AI88: 0
A89: 51 | B89: No | C89: Travel_Rarely | D89: 432 | E89: Research & Development | F89: 9 | G89: 4 | H89: Life Sciences | I89: 1 | J89: 116 | K89: 4 | L89: Male | M89: 96 | N89: 3 | O89: 1 | P89: Laboratory Technician | Q89: 4 | R89: Married | S89: 2075 | T89: 18725 | U89: 3 | V89: Y | W89: No | X89: 23 | Y89: 4 | Z89: 2 | AA89: 80 | AB89: 2 | AC89: 10 | AD89: 4 | AE89: 3 | AF89: 4 | AG89: 2 | AH89: 0 | AI89: 3
A90: 30 | B90: No | C90: Travel_Rarely | D90: 288 | E90: Research & Development | F90: 2 | G90: 3 | H90: Life Sciences | I90: 1 | J90: 117 | K90: 3 | L90: Male | M90: 99 | N90: 2 | O90: 2 | P90: Healthcare Representative | Q90: 4 | R90: Married | S90: 4152 | T90: 15830 | U90: 1 | V90: Y | W90: No | X90: 19 | Y90: 3 | Z90: 1 | AA90: 80 | AB90: 3 | AC90: 11 | AD90: 3 | AE90: 3 | AF90: 11 | AG90: 10 | AH90: 10 | AI90: 8
A91: 46 | B91: Yes | C91: Travel_Rarely | D91: 669 | E91: Sales | F91: 9 | G91: 2 | H91: Medical | I91: 1 | J91: 118 | K91: 3 | L91: Male | M91: 64 | N91: 2 | O91: 3 | P91: Sales Executive | Q91: 4 | R91: Single | S91: 9619 | T91: 13596 | U91: 1 | V91: Y | W91: No | X91: 16 | Y91: 3 | Z91: 4 | AA91: 80 | AB91: 0 | AC91: 9 | AD91: 3 | AE91: 3 | AF91: 9 | AG91: 8 | AH91: 4 | AI91: 7
A92: 40 | B92: No | C92: Travel_Frequently | D92: 530 | E92: Research & Development | F92: 1 | G92: 4 | H92: Life Sciences | I92: 1 | J92: 119 | K92: 3 | L92: Male | M92: 78 | N92: 2 | O92: 4 | P92: Healthcare Representative | Q92: 2 | R92: Married | S92: 13503 | T92: 14115 | U92: 1 | V92: Y | W92: No | X92: 22 | Y92: 4 | Z92: 4 | AA92: 80 | AB92: 1 | AC92: 22 | AD92: 3 | AE92: 2 | AF92: 22 | AG92: 3 | AH92: 11 | AI92: 11
A93: 51 | B93: No | C93: Travel_Rarely | D93: 632 | E93: Sales | F93: 21 | G93: 4 | H93: Marketing | I93: 1 | J93: 120 | K93: 3 | L93: Male | M93: 71 | N93: 3 | O93: 2 | P93: Sales Executive | Q93: 4 | R93: Single | S93: 5441 | T93: 8423 | U93: 0 | V93: Y | W93: Yes | X93: 22 | Y93: 4 | Z93: 4 | AA93: 80 | AB93: 0 | AC93: 11 | AD93: 2 | AE93: 1 | AF93: 10 | AG93: 7 | AH93: 1 | AI93: 0
A94: 30 | B94: No | C94: Travel_Rarely | D94: 1334 | E94: Sales | F94: 4 | G94: 2 | H94: Medical | I94: 1 | J94: 121 | K94: 3 | L94: Female | M94: 63 | N94: 2 | O94: 2 | P94: Sales Executive | Q94: 2 | R94: Divorced | S94: 5209 | T94: 19760 | U94: 1 | V94: Y | W94: Yes | X94: 12 | Y94: 3 | Z94: 2 | AA94: 80 | AB94: 3 | AC94: 11 | AD94: 4 | AE94: 2 | AF94: 11 | AG94: 8 | AH94: 2 | AI94: 7
A95: 46 | B95: No | C95: Travel_Frequently | D95: 638 | E95: Research & Development | F95: 1 | G95: 3 | H95: Medical | I95: 1 | J95: 124 | K95: 3 | L95: Male | M95: 40 | N95: 2 | O95: 3 | P95: Healthcare Representative | Q95: 1 | R95: Married | S95: 10673 | T95: 3142 | U95: 2 | V95: Y | W95: Yes | X95: 13 | Y95: 3 | Z95: 3 | AA95: 80 | AB95: 1 | AC95: 21 | AD95: 5 | AE95: 2 | AF95: 10 | AG95: 9 | AH95: 9 | AI95: 5
A96: 32 | B96: No | C96: Travel_Rarely | D96: 1093 | E96: Sales | F96: 6 | G96: 4 | H96: Medical | I96: 1 | J96: 125 | K96: 2 | L96: Male | M96: 87 | N96: 3 | O96: 2 | P96: Sales Executive | Q96: 3 | R96: Single | S96: 5010 | T96: 24301 | U96: 1 | V96: Y | W96: No | X96: 16 | Y96: 3 | Z96: 1 | AA96: 80 | AB96: 0 | AC96: 12 | AD96: 0 | AE96: 3 | AF96: 11 | AG96: 8 | AH96: 5 | AI96: 7
A97: 54 | B97: No | C97: Travel_Rarely | D97: 1217 | E97: Research & Development | F97: 12km | G97: 4 | H97: Technical Degree | I97: 1 | J97: 126 | K97: 1 | L97: Female | M97: 60 | N97: 3 | O97: 3 | P97: Research Director | Q97: 3 | R97: Married | S97: 13549 | T97: 24001 | U97: 9 | V97: Y | W97: No | X97: 12 | Y97: 3 | Z97: 1 | AA97: 80 | AB97: 1 | AC97: 16 | AD97: 5 | AE97: 1 | AF97: 4 | AG97: 3 | AH97: 0 | AI97: 3
A98: 24 | B98: No | C98: Travel_Rarely | D98: 1353 | E98: Sales | F98: 3 | G98: 2 | H98: Other | I98: 1 | J98: 128 | K98: 1 | L98: Female | M98: 33 | N98: 3 | O98: 2 | P98: Sales Executive | Q98: 3 | R98: Married | S98: 4999 | T98: 17519 | U98: 0 | V98: Y | W98: No | X98: 21 | Y98: 4 | Z98: 1 | AA98: 80 | AB98: 1 | AC98: 4 | AD98: 2 | AE98: 2 | AF98: 3 | AG98: 2 | AH98: 0 | AI98: 2
A99: 28 | B99: No | C99: Non-Travel | D99: 120 | E99: Sales | F99: 4 | G99: 3 | H99: Medical | I99: 1 | J99: 129 | K99: 2 | L99: Male | M99: 43 | N99: 3 | O99: 2 | P99: Sales Executive | Q99: 3 | R99: Married | S99: 4221 | T99: 8863 | U99: 1 | V99: Y | W99: No | X99: 15 | Y99: 3 | Z99: 2 | AA99: 80 | AB99: 0 | AC99: 5 | AD99: 3 | AE99: 4 | AF99: 5 | AG99: 4 | AH99: 0 | AI99: 4
A100: 58 | B100: No | C100: Travel_Rarely | D100: 682 | E100: Sales | F100: 10 | G100: 4 | H100: Medical | I100: 1 | J100: 131 | K100: 4 | L100: Male | M100: 37 | N100: 3 | O100: 4 | P100: Sales Executive | Q100: 3 | R100: Single | S100: 13872 | T100: 24409 | U100: 0 | V100: Y | W100: No | X100: 13 | Y100: 3 | Z100: 3 | AA100: 80 | AB100: 0 | AC100: 38 | AD100: 1 | AE100: 2 | AF100: 37 | AG100: 10 | AH100: 1 | AI100: 8
...

Sheet Data_Cleaned
A1: Age | B1: Attrition | C1: BusinessTravel | D1: DailyRate | E1: Department | F1: DistanceFromHome | G1: Education | H1: EducationField | I1: EmployeeCount | J1: EmployeeNumber | K1: EnvironmentSatisfaction | L1: Gender | M1: HourlyRate | N1: JobInvolvement | O1: JobLevel | P1: JobRole | Q1: JobSatisfaction | R1: MaritalStatus | S1: MonthlyIncome | T1: MonthlyRate | U1: NumCompaniesWorked | V1: Over18 | W1: OverTime | X1: PercentSalaryHike | Y1: PerformanceRating | Z1: RelationshipSatisfaction | AA1: StandardHours | AB1: StockOptionLevel | AC1: TotalWorkingYears | AD1: TrainingTimesLastYear | AE1: WorkLifeBalance | AF1: YearsAtCompany | AG1: YearsInCurrentRole | AH1: YearsSinceLastPromotion | AI1: YearsWithCurrManager | AJ1: Attrition_Flag | AK1: OverTime_Flag | AL1: Gender_Flag | AM1: SatisfactionIndex | AN1: IncomePerYearAtCompany | AO1: TenureRatio | AP1: AgeGroup | AQ1: IncomeBand | AR1: CommuteBurden | AS1: IsFrequentTraveler | AU1: Income Q1 (25th pct) | AV1: =_xlfn.QUARTILE.INC($S$2:$S$1471,1) -> 2905.25
A2: 41 | B2: Yes | C2: Travel_Rarely | D2: 1102 | E2: Sales | F2: 1 | G2: 2 | H2: Life Sciences | I2: 1 | J2: 1 | K2: 2 | L2: Female | M2: 94 | N2: 3 | O2: 2 | P2: Sales Executive | Q2: 4 | R2: Single | S2: 5993 | T2: 19479 | U2: 8 | V2: Y | W2: Yes | X2: 11 | Y2: 3 | Z2: 1 | AA2: 80 | AB2: 0 | AC2: 8 | AD2: 0 | AE2: 1 | AF2: 6 | AG2: 4 | AH2: 0 | AI2: 5 | AJ2: =IF(B2="Yes",1,0) -> 1 | AK2: =IF(W2="Yes",1,0) -> 1 | AL2: =IF(L2="Male",1,0) -> 0 | AM2: =AVERAGE(K2,Q2,Z2,AE2) -> 2 | AN2: =(S2*12)/(AF2+1) -> 10273.714 | AO2: =AF2/(AC2+1) -> 0.66666667 | AP2: =IF(A2<30,"Under 30",IF(A2<40,"30-39",IF(A2<50,"40-49","50+"))) -> 40-49 | AQ2: =IF(S2<=$AV$1,"Low",IF(S2<=$AV$2,"Medium",IF(S2<=$AV$3,"High","Very High"))) -> High | AR2: =IF(F2<=5,"Short",IF(F2<=15,"Medium","Long")) -> Short | AS2: =IF(C2="Travel_Frequently",1,0) -> 0 | AU2: Income Median (50th pct) | AV2: =_xlfn.QUARTILE.INC($S$2:$S$1471,2) -> 4919
A3: 49 | B3: No | C3: Travel_Frequently | D3: 279 | E3: Research & Development | F3: 8 | G3: 1 | H3: Life Sciences | I3: 1 | J3: 2 | K3: 3 | L3: Male | M3: 61 | N3: 2 | O3: 2 | P3: Research Scientist | Q3: 2 | R3: Married | S3: 5130 | T3: 24907 | U3: 1 | V3: Y | W3: No | X3: 23 | Y3: 4 | Z3: 4 | AA3: 80 | AB3: 1 | AC3: 10 | AD3: 3 | AE3: 3 | AF3: 10 | AG3: 7 | AH3: 1 | AI3: 7 | AJ3: =IF(B3="Yes",1,0) -> 0 | AK3: =IF(W3="Yes",1,0) -> 0 | AL3: =IF(L3="Male",1,0) -> 1 | AM3: =AVERAGE(K3,Q3,Z3,AE3) -> 3 | AN3: =(S3*12)/(AF3+1) -> 5596.3636 | AO3: =AF3/(AC3+1) -> 0.90909091 | AP3: =IF(A3<30,"Under 30",IF(A3<40,"30-39",IF(A3<50,"40-49","50+"))) -> 40-49 | AQ3: =IF(S3<=$AV$1,"Low",IF(S3<=$AV$2,"Medium",IF(S3<=$AV$3,"High","Very High"))) -> High | AR3: =IF(F3<=5,"Short",IF(F3<=15,"Medium","Long")) -> Medium | AS3: =IF(C3="Travel_Frequently",1,0) -> 1 | AU3: Income Q3 (75th pct) | AV3: =_xlfn.QUARTILE.INC($S$2:$S$1471,3) -> 8339.75
A4: 37 | B4: Yes | C4: Travel_Rarely | D4: 1373 | E4: Research & Development | F4: 2 | G4: 2 | H4: Other | I4: 1 | J4: 4 | K4: 4 | L4: Male | M4: 92 | N4: 2 | O4: 1 | P4: Laboratory Technician | Q4: 3 | R4: Single | S4: 2090 | T4: 2396 | U4: 6 | V4: Y | W4: Yes | X4: 15 | Y4: 3 | Z4: 2 | AA4: 80 | AB4: 0 | AC4: 7 | AD4: 3 | AE4: 3 | AF4: 0 | AG4: 0 | AH4: 0 | AI4: 0 | AJ4: =IF(B4="Yes",1,0) -> 1 | AK4: =IF(W4="Yes",1,0) -> 1 | AL4: =IF(L4="Male",1,0) -> 1 | AM4: =AVERAGE(K4,Q4,Z4,AE4) -> 3 | AN4: =(S4*12)/(AF4+1) -> 25080 | AO4: =AF4/(AC4+1) -> 0 | AP4: =IF(A4<30,"Under 30",IF(A4<40,"30-39",IF(A4<50,"40-49","50+"))) -> 30-39 | AQ4: =IF(S4<=$AV$1,"Low",IF(S4<=$AV$2,"Medium",IF(S4<=$AV$3,"High","Very High"))) -> Low | AR4: =IF(F4<=5,"Short",IF(F4<=15,"Medium","Long")) -> Short | AS4: =IF(C4="Travel_Frequently",1,0) -> 0
A5: 33 | B5: No | C5: Travel_Frequently | D5: 1392 | E5: Research & Development | F5: 3 | G5: 4 | H5: Life Sciences | I5: 1 | J5: 5 | K5: 4 | L5: Female | M5: 56 | N5: 3 | O5: 1 | P5: Research Scientist | Q5: 3 | R5: Married | S5: 2909 | T5: 23159 | U5: 1 | V5: Y | W5: Yes | X5: 11 | Y5: 3 | Z5: 3 | AA5: 80 | AB5: 0 | AC5: 8 | AD5: 3 | AE5: 3 | AF5: 8 | AG5: 7 | AH5: 3 | AI5: 0 | AJ5: =IF(B5="Yes",1,0) -> 0 | AK5: =IF(W5="Yes",1,0) -> 1 | AL5: =IF(L5="Male",1,0) -> 0 | AM5: =AVERAGE(K5,Q5,Z5,AE5) -> 3.25 | AN5: =(S5*12)/(AF5+1) -> 3878.6667 | AO5: =AF5/(AC5+1) -> 0.88888889 | AP5: =IF(A5<30,"Under 30",IF(A5<40,"30-39",IF(A5<50,"40-49","50+"))) -> 30-39 | AQ5: =IF(S5<=$AV$1,"Low",IF(S5<=$AV$2,"Medium",IF(S5<=$AV$3,"High","Very High"))) -> Medium | AR5: =IF(F5<=5,"Short",IF(F5<=15,"Medium","Long")) -> Short | AS5: =IF(C5="Travel_Frequently",1,0) -> 1
A6: 27 | B6: No | C6: Travel_Rarely | D6: 591 | E6: Research & Development | F6: 2 | G6: 1 | H6: Medical | I6: 1 | J6: 7 | K6: 1 | L6: Male | M6: 40 | N6: 3 | O6: 1 | P6: Laboratory Technician | Q6: 2 | R6: Married | S6: 3468 | T6: 16632 | U6: 9 | V6: Y | W6: No | X6: 12 | Y6: 3 | Z6: 4 | AA6: 80 | AB6: 1 | AC6: 6 | AD6: 3 | AE6: 3 | AF6: 2 | AG6: 2 | AH6: 2 | AI6: 2 | AJ6: =IF(B6="Yes",1,0) -> 0 | AK6: =IF(W6="Yes",1,0) -> 0 | AL6: =IF(L6="Male",1,0) -> 1 | AM6: =AVERAGE(K6,Q6,Z6,AE6) -> 2.5 | AN6: =(S6*12)/(AF6+1) -> 13872 | AO6: =AF6/(AC6+1) -> 0.28571429 | AP6: =IF(A6<30,"Under 30",IF(A6<40,"30-39",IF(A6<50,"40-49","50+"))) -> Under 30 | AQ6: =IF(S6<=$AV$1,"Low",IF(S6<=$AV$2,"Medium",IF(S6<=$AV$3,"High","Very High"))) -> Medium | AR6: =IF(F6<=5,"Short",IF(F6<=15,"Medium","Long")) -> Short | AS6: =IF(C6="Travel_Frequently",1,0) -> 0
A7: 32 | B7: No | C7: Travel_Frequently | D7: 1005 | E7: Research & Development | F7: 2 | G7: 2 | H7: Life Sciences | I7: 1 | J7: 8 | K7: 4 | L7: Male | M7: 79 | N7: 3 | O7: 1 | P7: Laboratory Technician | Q7: 4 | R7: Single | S7: 3068 | T7: 11864 | U7: 0 | V7: Y | W7: No | X7: 13 | Y7: 3 | Z7: 3 | AA7: 80 | AB7: 0 | AC7: 8 | AD7: 2 | AE7: 2 | AF7: 7 | AG7: 7 | AH7: 3 | AI7: 6 | AJ7: =IF(B7="Yes",1,0) -> 0 | AK7: =IF(W7="Yes",1,0) -> 0 | AL7: =IF(L7="Male",1,0) -> 1 | AM7: =AVERAGE(K7,Q7,Z7,AE7) -> 3.25 | AN7: =(S7*12)/(AF7+1) -> 4602 | AO7: =AF7/(AC7+1) -> 0.77777778 | AP7: =IF(A7<30,"Under 30",IF(A7<40,"30-39",IF(A7<50,"40-49","50+"))) -> 30-39 | AQ7: =IF(S7<=$AV$1,"Low",IF(S7<=$AV$2,"Medium",IF(S7<=$AV$3,"High","Very High"))) -> Medium | AR7: =IF(F7<=5,"Short",IF(F7<=15,"Medium","Long")) -> Short | AS7: =IF(C7="Travel_Frequently",1,0) -> 1
A8: 59 | B8: No | C8: Travel_Rarely | D8: 1324 | E8: Research & Development | F8: 3 | G8: 3 | H8: Medical | I8: 1 | J8: 10 | K8: 3 | L8: Female | M8: 81 | N8: 4 | O8: 1 | P8: Laboratory Technician | Q8: 1 | R8: Married | S8: 2670 | T8: 9964 | U8: 4 | V8: Y | W8: Yes | X8: 20 | Y8: 4 | Z8: 1 | AA8: 80 | AB8: 3 | AC8: 12 | AD8: 3 | AE8: 2 | AF8: 1 | AG8: 0 | AH8: 0 | AI8: 0 | AJ8: =IF(B8="Yes",1,0) -> 0 | AK8: =IF(W8="Yes",1,0) -> 1 | AL8: =IF(L8="Male",1,0) -> 0 | AM8: =AVERAGE(K8,Q8,Z8,AE8) -> 1.75 | AN8: =(S8*12)/(AF8+1) -> 16020 | AO8: =AF8/(AC8+1) -> 0.076923077 | AP8: =IF(A8<30,"Under 30",IF(A8<40,"30-39",IF(A8<50,"40-49","50+"))) -> 50+ | AQ8: =IF(S8<=$AV$1,"Low",IF(S8<=$AV$2,"Medium",IF(S8<=$AV$3,"High","Very High"))) -> Low | AR8: =IF(F8<=5,"Short",IF(F8<=15,"Medium","Long")) -> Short | AS8: =IF(C8="Travel_Frequently",1,0) -> 0
A9: 30 | B9: No | C9: Travel_Rarely | D9: 1358 | E9: Research & Development | F9: 24 | G9: 1 | H9: Life Sciences | I9: 1 | J9: 11 | K9: 4 | L9: Male | M9: 67 | N9: 3 | O9: 1 | P9: Laboratory Technician | Q9: 3 | R9: Divorced | S9: 2693 | T9: 13335 | U9: 1 | V9: Y | W9: No | X9: 22 | Y9: 4 | Z9: 2 | AA9: 80 | AB9: 1 | AC9: 1 | AD9: 2 | AE9: 3 | AF9: 1 | AG9: 0 | AH9: 0 | AI9: 0 | AJ9: =IF(B9="Yes",1,0) -> 0 | AK9: =IF(W9="Yes",1,0) -> 0 | AL9: =IF(L9="Male",1,0) -> 1 | AM9: =AVERAGE(K9,Q9,Z9,AE9) -> 3 | AN9: =(S9*12)/(AF9+1) -> 16158 | AO9: =AF9/(AC9+1) -> 0.5 | AP9: =IF(A9<30,"Under 30",IF(A9<40,"30-39",IF(A9<50,"40-49","50+"))) -> 30-39 | AQ9: =IF(S9<=$AV$1,"Low",IF(S9<=$AV$2,"Medium",IF(S9<=$AV$3,"High","Very High"))) -> Low | AR9: =IF(F9<=5,"Short",IF(F9<=15,"Medium","Long")) -> Long | AS9: =IF(C9="Travel_Frequently",1,0) -> 0
A10: 38 | B10: No | C10: Travel_Frequently | D10: 216 | E10: Research & Development | F10: 23 | G10: 3 | H10: Life Sciences | I10: 1 | J10: 12 | K10: 4 | L10: Male | M10: 44 | N10: 2 | O10: 3 | P10: Manufacturing Director | Q10: 3 | R10: Single | S10: 9526 | T10: 8787 | U10: 0 | V10: Y | W10: No | X10: 21 | Y10: 4 | Z10: 2 | AA10: 80 | AB10: 0 | AC10: 10 | AD10: 2 | AE10: 3 | AF10: 9 | AG10: 7 | AH10: 1 | AI10: 8 | AJ10: =IF(B10="Yes",1,0) -> 0 | AK10: =IF(W10="Yes",1,0) -> 0 | AL10: =IF(L10="Male",1,0) -> 1 | AM10: =AVERAGE(K10,Q10,Z10,AE10) -> 3 | AN10: =(S10*12)/(AF10+1) -> 11431.2 | AO10: =AF10/(AC10+1) -> 0.81818182 | AP10: =IF(A10<30,"Under 30",IF(A10<40,"30-39",IF(A10<50,"40-49","50+"))) -> 30-39 | AQ10: =IF(S10<=$AV$1,"Low",IF(S10<=$AV$2,"Medium",IF(S10<=$AV$3,"High","Very High"))) -> Very High | AR10: =IF(F10<=5,"Short",IF(F10<=15,"Medium","Long")) -> Long | AS10: =IF(C10="Travel_Frequently",1,0) -> 1
A11: 36 | B11: No | C11: Travel_Rarely | D11: 1299 | E11: Research & Development | F11: 27 | G11: 3 | H11: Medical | I11: 1 | J11: 13 | K11: 3 | L11: Male | M11: 94 | N11: 3 | O11: 2 | P11: Healthcare Representative | Q11: 3 | R11: Married | S11: 5237 | T11: 16577 | U11: 6 | V11: Y | W11: No | X11: 13 | Y11: 3 | Z11: 2 | AA11: 80 | AB11: 2 | AC11: 17 | AD11: 3 | AE11: 2 | AF11: 7 | AG11: 7 | AH11: 7 | AI11: 7 | AJ11: =IF(B11="Yes",1,0) -> 0 | AK11: =IF(W11="Yes",1,0) -> 0 | AL11: =IF(L11="Male",1,0) -> 1 | AM11: =AVERAGE(K11,Q11,Z11,AE11) -> 2.5 | AN11: =(S11*12)/(AF11+1) -> 7855.5 | AO11: =AF11/(AC11+1) -> 0.38888889 | AP11: =IF(A11<30,"Under 30",IF(A11<40,"30-39",IF(A11<50,"40-49","50+"))) -> 30-39 | AQ11: =IF(S11<=$AV$1,"Low",IF(S11<=$AV$2,"Medium",IF(S11<=$AV$3,"High","Very High"))) -> High | AR11: =IF(F11<=5,"Short",IF(F11<=15,"Medium","Long")) -> Long | AS11: =IF(C11="Travel_Frequently",1,0) -> 0
A12: 35 | B12: No | C12: Travel_Rarely | D12: 809 | E12: Research & Development | F12: 16 | G12: 3 | H12: Medical | I12: 1 | J12: 14 | K12: 1 | L12: Male | M12: 84 | N12: 4 | O12: 1 | P12: Laboratory Technician | Q12: 2 | R12: Married | S12: 2674 | T12: 16479 | U12: 0 | V12: Y | W12: No | X12: 13 | Y12: 3 | Z12: 3 | AA12: 80 | AB12: 1 | AC12: 6 | AD12: 5 | AE12: 3 | AF12: 5 | AG12: 4 | AH12: 0 | AI12: 3 | AJ12: =IF(B12="Yes",1,0) -> 0 | AK12: =IF(W12="Yes",1,0) -> 0 | AL12: =IF(L12="Male",1,0) -> 1 | AM12: =AVERAGE(K12,Q12,Z12,AE12) -> 2.25 | AN12: =(S12*12)/(AF12+1) -> 5348 | AO12: =AF12/(AC12+1) -> 0.71428571 | AP12: =IF(A12<30,"Under 30",IF(A12<40,"30-39",IF(A12<50,"40-49","50+"))) -> 30-39 | AQ12: =IF(S12<=$AV$1,"Low",IF(S12<=$AV$2,"Medium",IF(S12<=$AV$3,"High","Very High"))) -> Low | AR12: =IF(F12<=5,"Short",IF(F12<=15,"Medium","Long")) -> Long | AS12: =IF(C12="Travel_Frequently",1,0) -> 0
A13: 29 | B13: No | C13: Travel_Rarely | D13: 153 | E13: Research & Development | F13: 15 | G13: 2 | H13: Life Sciences | I13: 1 | J13: 15 | K13: 4 | L13: Female | M13: 49 | N13: 2 | O13: 2 | P13: Laboratory Technician | Q13: 3 | R13: Single | S13: 4193 | T13: 12682 | U13: 0 | V13: Y | W13: Yes | X13: 12 | Y13: 3 | Z13: 4 | AA13: 80 | AB13: 0 | AC13: 10 | AD13: 3 | AE13: 3 | AF13: 9 | AG13: 5 | AH13: 0 | AI13: 8 | AJ13: =IF(B13="Yes",1,0) -> 0 | AK13: =IF(W13="Yes",1,0) -> 1 | AL13: =IF(L13="Male",1,0) -> 0 | AM13: =AVERAGE(K13,Q13,Z13,AE13) -> 3.5 | AN13: =(S13*12)/(AF13+1) -> 5031.6 | AO13: =AF13/(AC13+1) -> 0.81818182 | AP13: =IF(A13<30,"Under 30",IF(A13<40,"30-39",IF(A13<50,"40-49","50+"))) -> Under 30 | AQ13: =IF(S13<=$AV$1,"Low",IF(S13<=$AV$2,"Medium",IF(S13<=$AV$3,"High","Very High"))) -> Medium | AR13: =IF(F13<=5,"Short",IF(F13<=15,"Medium","Long")) -> Medium | AS13: =IF(C13="Travel_Frequently",1,0) -> 0
A14: 31 | B14: No | C14: Travel_Rarely | D14: 670 | E14: Research & Development | F14: 26 | G14: 1 | H14: Life Sciences | I14: 1 | J14: 16 | K14: 1 | L14: Male | M14: 31 | N14: 3 | O14: 1 | P14: Research Scientist | Q14: 3 | R14: Divorced | S14: 2911 | T14: 15170 | U14: 1 | V14: Y | W14: No | X14: 17 | Y14: 3 | Z14: 4 | AA14: 80 | AB14: 1 | AC14: 5 | AD14: 1 | AE14: 2 | AF14: 5 | AG14: 2 | AH14: 4 | AI14: 3 | AJ14: =IF(B14="Yes",1,0) -> 0 | AK14: =IF(W14="Yes",1,0) -> 0 | AL14: =IF(L14="Male",1,0) -> 1 | AM14: =AVERAGE(K14,Q14,Z14,AE14) -> 2.5 | AN14: =(S14*12)/(AF14+1) -> 5822 | AO14: =AF14/(AC14+1) -> 0.83333333 | AP14: =IF(A14<30,"Under 30",IF(A14<40,"30-39",IF(A14<50,"40-49","50+"))) -> 30-39 | AQ14: =IF(S14<=$AV$1,"Low",IF(S14<=$AV$2,"Medium",IF(S14<=$AV$3,"High","Very High"))) -> Medium | AR14: =IF(F14<=5,"Short",IF(F14<=15,"Medium","Long")) -> Long | AS14: =IF(C14="Travel_Frequently",1,0) -> 0
A15: 34 | B15: No | C15: Travel_Rarely | D15: 1346 | E15: Research & Development | F15: 19 | G15: 2 | H15: Medical | I15: 1 | J15: 18 | K15: 2 | L15: Male | M15: 93 | N15: 3 | O15: 1 | P15: Laboratory Technician | Q15: 4 | R15: Divorced | S15: 2661 | T15: 8758 | U15: 0 | V15: Y | W15: No | X15: 11 | Y15: 3 | Z15: 3 | AA15: 80 | AB15: 1 | AC15: 3 | AD15: 2 | AE15: 3 | AF15: 2 | AG15: 2 | AH15: 1 | AI15: 2 | AJ15: =IF(B15="Yes",1,0) -> 0 | AK15: =IF(W15="Yes",1,0) -> 0 | AL15: =IF(L15="Male",1,0) -> 1 | AM15: =AVERAGE(K15,Q15,Z15,AE15) -> 3 | AN15: =(S15*12)/(AF15+1) -> 10644 | AO15: =AF15/(AC15+1) -> 0.5 | AP15: =IF(A15<30,"Under 30",IF(A15<40,"30-39",IF(A15<50,"40-49","50+"))) -> 30-39 | AQ15: =IF(S15<=$AV$1,"Low",IF(S15<=$AV$2,"Medium",IF(S15<=$AV$3,"High","Very High"))) -> Low | AR15: =IF(F15<=5,"Short",IF(F15<=15,"Medium","Long")) -> Long | AS15: =IF(C15="Travel_Frequently",1,0) -> 0
... A1471: 34 | B1471: No | C1471: Travel_Rarely | D1471: 628 | E1471: Research & Development | F1471: 8 | G1471: 3 | H1471: Medical | I1471: 1 | J1471: 2068 | K1471: 2 | L1471: Male | M1471: 82 | N1471: 4 | O1471: 2 | P1471: Laboratory Technician | Q1471: 3 | R1471: Married | S1471: 4404 | T1471: 10228 | U1471: 2 | V1471: Y | W1471: No | X1471: 12 | Y1471: 3 | Z1471: 1 | AA1471: 80 | AB1471: 0 | AC1471: 6 | AD1471: 3 | AE1471: 4 | AF1471: 4 | AG1471: 3 | AH1471: 1 | AI1471: 2 | AJ1471: =IF(B1471="Yes",1,0) -> 0 | AK1471: =IF(W1471="Yes",1,0) -> 0 | AL1471: =IF(L1471="Male",1,0) -> 1 | AM1471: =AVERAGE(K1471,Q1471,Z1471,AE1471) -> 2.5 | AN1471: =(S1471*12)/(AF1471+1) -> 10569.6 | AO1471: =AF1471/(AC1471+1) -> 0.57142857 | AP1471: =IF(A1471<30,"Under 30",IF(A1471<40,"30-39",IF(A1471<50,"40-49","50+"))) -> 30-39 | AQ1471: =IF(S1471<=$AV$1,"Low",IF(S1471<=$AV$2,"Medium",IF(S1471<=$AV$3,"High","Very High"))) -> Medium | AR1471: =IF(F1471<=5,"Short",IF(F1471<=15,"Medium","Long")) -> Medium | AS1471: =IF(C1471="Travel_Frequently",1,0) -> 0

Sheet EDA_Summary
A1: EXPLORATORY DATA ANALYSIS | M1: Attrition | N1: MonthlyIncome | P1: YearsAtCompany_Left | Q1: MonthlyIncome_Left | R1: YearsAtCompany_Stayed | S1: MonthlyIncome_Stayed | V1: Age Bin | W1: Employee Count | Y1: Department | Z1: AttritionRate | AB1: JobRole | AC1: AttritionRate | AE1: Status | AF1: Employees | AH1: TenureBucket | AI1: AttritionRate
M2: =Data_Cleaned!B2 -> Yes | N2: =Data_Cleaned!S2 -> 5993 | P2: {=_xlfn._xlws.FILTER(Data_Cleaned!AF2:AF1471,Data_Cleaned!B2:B1471="Yes")} -> 6 | Q2: {=_xlfn._xlws.FILTER(Data_Cleaned!S2:S1471,Data_Cleaned!B2:B1471="Yes")} -> 5993 | R2: {=_xlfn._xlws.FILTER(Data_Cleaned!AF2:AF1471,Data_Cleaned!B2:B1471="No")} -> 10 | S2: {=_xlfn._xlws.FILTER(Data_Cleaned!S2:S1471,Data_Cleaned!B2:B1471="No")} -> 5130 | V2: 18-24 | W2: =COUNTIFS(Data_Cleaned!$A$2:$A$1471,">=18",Data_Cleaned!$A$2:$A$1471,"<=24") -> 97 | Y2: =A40 -> Sales | Z2: =C40 -> 0.20898876 | AB2: =A53 -> Sales Executive | AC2: =C53 -> 0.17484663 | AE2: Left | AF2: =B31 -> 237 | AH2: =A89 -> 0-2 yrs | AI2: =C89 -> 0.29824561
A3: 1. DATASET DIMENSIONS | M3: =Data_Cleaned!B3 -> No | N3: =Data_Cleaned!S3 -> 5130 | P3: 0 | Q3: 2090 | R3: 8 | S3: 2909 | V3: 25-34 | W3: =COUNTIFS(Data_Cleaned!$A$2:$A$1471,">=25",Data_Cleaned!$A$2:$A$1471,"<=34") -> 553 | Y3: =A41 -> Research & Development | Z3: =C41 -> 0.13825364 | AB3: =A54 -> Research Scientist | AC3: =C54 -> 0.1609589 | AE3: Stayed | AF3: =B32 -> 1233 | AH3: =A90 -> 3-5 yrs | AI3: =C90 -> 0.13824885
A4: Rows (employees) | B4: =COUNTA(Data_Cleaned!A:A)-1 -> 1470 | M4: =Data_Cleaned!B4 -> Yes | N4: =Data_Cleaned!S4 -> 2090 | P4: 4 | Q4: 2028 | R4: 2 | S4: 3468 | V4: 35-44 | W4: =COUNTIFS(Data_Cleaned!$A$2:$A$1471,">=35",Data_Cleaned!$A$2:$A$1471,"<=44") -> 508 | Y4: =A42 -> Human Resources | Z4: =C42 -> 0.17460317 | AB4: =A55 -> Laboratory Technician | AC4: =C55 -> 0.23938224 | AH4: =A91 -> 6-10 yrs | AI4: =C91 -> 0.12276786
A5: Columns (base + engineered) | B5: =COUNTA(Data_Cleaned!1:1) -> 47 | M5: =Data_Cleaned!B5 -> No | N5: =Data_Cleaned!S5 -> 2909 | P5: 5 | Q5: 3407 | R5: 7 | S5: 3068 | V5: 45-54 | W5: =COUNTIFS(Data_Cleaned!$A$2:$A$1471,">=45",Data_Cleaned!$A$2:$A$1471,"<=54") -> 244 | AB5: =A56 -> Manufacturing Director | AC5: =C56 -> 0.068965517 | AH5: =A92 -> 11+ yrs | AI5: =C92 -> 0.081300813
A6: Numeric variables profiled below | B6: 14 | M6: =Data_Cleaned!B6 -> No | N6: =Data_Cleaned!S6 -> 3468 | P6: 4 | Q6: 2960 | R6: 1 | S6: 2670 | V6: 55+ | W6: =COUNTIFS(Data_Cleaned!$A$2:$A$1471,">=55") -> 68 | AB6: =A57 -> Healthcare Representative | AC6: =C57 -> 0.06870229
M7: =Data_Cleaned!B7 -> No | N7: =Data_Cleaned!S7 -> 3068 | P7: 10 | Q7: 3919 | R7: 1 | S7: 2693 | AB7: =A58 -> Manager | AC7: =C58 -> 0.049019608
A8: 2. SUMMARY STATISTICS (key numeric variables) | M8: =Data_Cleaned!B8 -> No | N8: =Data_Cleaned!S8 -> 2670 | P8: 1 | Q8: 2086 | R8: 9 | S8: 9526 | AB8: =A59 -> Sales Representative | AC8: =C59 -> 0.39759036
A9: Variable | B9: Count | C9: Mean | D9: Median | E9: StdDev | F9: Min | G9: Max | H9: Q1 | I9: Q3 | M9: =Data_Cleaned!B9 -> No | N9: =Data_Cleaned!S9 -> 2693 | P9: 2 | Q9: 2293 | R9: 7 | S9: 5237 | AB9: =A60 -> Research Director | AC9: =C60 -> 0.025
A10: Age | B10: =COUNT(Data_Cleaned!A2:A1471) -> 1470 | C10: =AVERAGE(Data_Cleaned!A2:A1471) -> 36.894558 | D10: =MEDIAN(Data_Cleaned!A2:A1471) -> 36 | E10: =_xlfn.STDEV.S(Data_Cleaned!A2:A1471) -> 9.1097482 | F10: =MIN(Data_Cleaned!A2:A1471) -> 18 | G10: =MAX(Data_Cleaned!A2:A1471) -> 60 | H10: =_xlfn.QUARTILE.INC(Data_Cleaned!A2:A1471,1) -> 30 | I10: =_xlfn.QUARTILE.INC(Data_Cleaned!A2:A1471,3) -> 43 | M10: =Data_Cleaned!B10 -> No | N10: =Data_Cleaned!S10 -> 9526 | P10: 3 | Q10: 2683 | R10: 5 | S10: 2674 | AB10: =A61 -> Human Resources | AC10: =C61 -> 0.23076923
A11: DailyRate | B11: =COUNT(Data_Cleaned!D2:D1471) -> 1470 | C11: =AVERAGE(Data_Cleaned!D2:D1471) -> 802.48571 | D11: =MEDIAN(Data_Cleaned!D2:D1471) -> 802 | E11: =_xlfn.STDEV.S(Data_Cleaned!D2:D1471) -> 403.5091 | F11: =MIN(Data_Cleaned!D2:D1471) -> 102 | G11: =MAX(Data_Cleaned!D2:D1471) -> 1499 | H11: =_xlfn.QUARTILE.INC(Data_Cleaned!D2:D1471,1) -> 465 | I11: =_xlfn.QUARTILE.INC(Data_Cleaned!D2:D1471,3) -> 1157 | M11: =Data_Cleaned!B11 -> No | N11: =Data_Cleaned!S11 -> 5237 | P11: 1 | Q11: 2293 | R11: 9 | S11: 4193
A12: DistanceFromHome | B12: =COUNT(Data_Cleaned!F2:F1471) -> 1470 | C12: =AVERAGE(Data_Cleaned!F2:F1471) -> 9.1993197 | D12: =MEDIAN(Data_Cleaned!F2:F1471) -> 7 | E12: =_xlfn.STDEV.S(Data_Cleaned!F2:F1471) -> 8.1055242 | F12: =MIN(Data_Cleaned!F2:F1471) -> 1 | G12: =MAX(Data_Cleaned!F2:F1471) -> 29 | H12: =_xlfn.QUARTILE.INC(Data_Cleaned!F2:F1471,1) -> 2 | I12: =_xlfn.QUARTILE.INC(Data_Cleaned!F2:F1471,3) -> 14 | M12: =Data_Cleaned!B12 -> No | N12: =Data_Cleaned!S12 -> 2674 | P12: 22 | Q12: 19545 | R12: 5 | S12: 2911
A13: MonthlyIncome | B13: =COUNT(Data_Cleaned!S2:S1471) -> 1470 | C13: =AVERAGE(Data_Cleaned!S2:S1471) -> 6490.4286 | D13: =MEDIAN(Data_Cleaned!S2:S1471) -> 4919 | E13: =_xlfn.STDEV.S(Data_Cleaned!S2:S1471) -> 4700.4471 | F13: =MIN(Data_Cleaned!S2:S1471) -> 1009 | G13: =MAX(Data_Cleaned!S2:S1471) -> 19999 | H13: =_xlfn.QUARTILE.INC(Data_Cleaned!S2:S1471,1) -> 2905.25 | I13: =_xlfn.QUARTILE.INC(Data_Cleaned!S2:S1471,3) -> 8339.75 | M13: =Data_Cleaned!B13 -> No | N13: =Data_Cleaned!S13 -> 4193 | P13: 1 | Q13: 5381 | R13: 2 | S13: 2661
A14: NumCompaniesWorked | B14: =COUNT(Data_Cleaned!U2:U1471) -> 1470 | C14: =AVERAGE(Data_Cleaned!U2:U1471) -> 2.6945578 | D14: =MEDIAN(Data_Cleaned!U2:U1471) -> 2 | E14: =_xlfn.STDEV.S(Data_Cleaned!U2:U1471) -> 2.4970856 | F14: =MIN(Data_Cleaned!U2:U1471) -> 0 | G14: =MAX(Data_Cleaned!U2:U1471) -> 9 | H14: =_xlfn.QUARTILE.INC(Data_Cleaned!U2:U1471,1) -> 1 | I14: =_xlfn.QUARTILE.INC(Data_Cleaned!U2:U1471,3) -> 4 | M14: =Data_Cleaned!B14 -> No | N14: =Data_Cleaned!S14 -> 2911 | P14: 2 | Q14: 3441 | R14: 10 | S14: 9980
A15: PercentSalaryHike | B15: =COUNT(Data_Cleaned!X2:X1471) -> 1470 | C15: =AVERAGE(Data_Cleaned!X2:X1471) -> 15.204082 | D15: =MEDIAN(Data_Cleaned!X2:X1471) -> 14 | E15: =_xlfn.STDEV.S(Data_Cleaned!X2:X1471) -> 3.6576408 | F15: =MIN(Data_Cleaned!X2:X1471) -> 11 | G15: =MAX(Data_Cleaned!X2:X1471) -> 25 | H15: =_xlfn.QUARTILE.INC(Data_Cleaned!X2:X1471,1) -> 12 | I15: =_xlfn.QUARTILE.INC(Data_Cleaned!X2:X1471,3) -> 18 | M15: =Data_Cleaned!B15 -> No | N15: =Data_Cleaned!S15 -> 2661 | P15: 1 | Q15: 3388 | R15: 6 | S15: 3298
A16: TotalWorkingYears | B16: =COUNT(Data_Cleaned!AC2:AC1471) -> 1470 | C16: =AVERAGE(Data_Cleaned!AC2:AC1471) -> 11.303401 | D16: =MEDIAN(Data_Cleaned!AC2:AC1471) -> 10 | E16: =_xlfn.STDEV.S(Data_Cleaned!AC2:AC1471) -> 7.7667969 | F16: =MIN(Data_Cleaned!AC2:AC1471) -> 0 | G16: =MAX(Data_Cleaned!AC2:AC1471) -> 40 | H16: =_xlfn.QUARTILE.INC(Data_Cleaned!AC2:AC1471,1) -> 6 | I16: =_xlfn.QUARTILE.INC(Data_Cleaned!AC2:AC1471,3) -> 15 | M16: =Data_Cleaned!B16 -> Yes | N16: =Data_Cleaned!S16 -> 2028 | P16: 9 | Q16: 9619 | R16: 1 | S16: 2935
A17: TrainingTimesLastYear | B17: =COUNT(Data_Cleaned!AD2:AD1471) -> 1470 | C17: =AVERAGE(Data_Cleaned!AD2:AD1471) -> 2.7993197 | D17: =MEDIAN(Data_Cleaned!AD2:AD1471) -> 3 | E17: =_xlfn.STDEV.S(Data_Cleaned!AD2:AD1471) -> 1.2892706 | F17: =MIN(Data_Cleaned!AD2:AD1471) -> 0 | G17: =MAX(Data_Cleaned!AD2:AD1471) -> 6 | H17: =_xlfn.QUARTILE.INC(Data_Cleaned!AD2:AD1471,1) -> 2 | I17: =_xlfn.QUARTILE.INC(Data_Cleaned!AD2:AD1471,3) -> 3 | M17: =Data_Cleaned!B17 -> No | N17: =Data_Cleaned!S17 -> 9980 | P17: 3 | Q17: 2073 | R17: 25 | S17: 15427
A18: YearsAtCompany | B18: =COUNT(Data_Cleaned!AF2:AF1471) -> 1470 | C18: =AVERAGE(Data_Cleaned!AF2:AF1471) -> 7.0081633 | D18: =MEDIAN(Data_Cleaned!AF2:AF1471) -> 5 | E18: =_xlfn.STDEV.S(Data_Cleaned!AF2:AF1471) -> 6.1265252 | F18: =MIN(Data_Cleaned!AF2:AF1471) -> 0 | G18: =MAX(Data_Cleaned!AF2:AF1471) -> 40 | H18: =_xlfn.QUARTILE.INC(Data_Cleaned!AF2:AF1471,1) -> 3 | I18: =_xlfn.QUARTILE.INC(Data_Cleaned!AF2:AF1471,3) -> 9 | M18: =Data_Cleaned!B18 -> No | N18: =Data_Cleaned!S18 -> 3298 | P18: 1 | Q18: 2926 | R18: 3 | S18: 3944
A19: YearsInCurrentRole | B19: =COUNT(Data_Cleaned!AG2:AG1471) -> 1470 | C19: =AVERAGE(Data_Cleaned!AG2:AG1471) -> 4.2292517 | D19: =MEDIAN(Data_Cleaned!AG2:AG1471) -> 3 | E19: =_xlfn.STDEV.S(Data_Cleaned!AG2:AG1471) -> 3.623137 | F19: =MIN(Data_Cleaned!AG2:AG1471) -> 0 | G19: =MAX(Data_Cleaned!AG2:AG1471) -> 18 | H19: =_xlfn.QUARTILE.INC(Data_Cleaned!AG2:AG1471,1) -> 2 | I19: =_xlfn.QUARTILE.INC(Data_Cleaned!AG2:AG1471,3) -> 7 | M19: =Data_Cleaned!B19 -> No | N19: =Data_Cleaned!S19 -> 2935 | P19: 6 | Q19: 5744 | R19: 4 | S19: 4011
A20: YearsSinceLastPromotion | B20: =COUNT(Data_Cleaned!AH2:AH1471) -> 1470 | C20: =AVERAGE(Data_Cleaned!AH2:AH1471) -> 2.1877551 | D20: =MEDIAN(Data_Cleaned!AH2:AH1471) -> 1 | E20: =_xlfn.STDEV.S(Data_Cleaned!AH2:AH1471) -> 3.2224303 | F20: =MIN(Data_Cleaned!AH2:AH1471) -> 0 | G20: =MAX(Data_Cleaned!AH2:AH1471) -> 15 | H20: =_xlfn.QUARTILE.INC(Data_Cleaned!AH2:AH1471,1) -> 0 | I20: =_xlfn.QUARTILE.INC(Data_Cleaned!AH2:AH1471,3) -> 3 | M20: =Data_Cleaned!B20 -> No | N20: =Data_Cleaned!S20 -> 15427 | P20: 9 | Q20: 6074 | R20: 12 | S20: 11994
A21: JobSatisfaction | B21: =COUNT(Data_Cleaned!Q2:Q1471) -> 1470 | C21: =AVERAGE(Data_Cleaned!Q2:Q1471) -> 2.7285714 | D21: =MEDIAN(Data_Cleaned!Q2:Q1471) -> 3 | E21: =_xlfn.STDEV.S(Data_Cleaned!Q2:Q1471) -> 1.1028461 | F21: =MIN(Data_Cleaned!Q2:Q1471) -> 1 | G21: =MAX(Data_Cleaned!Q2:Q1471) -> 4 | H21: =_xlfn.QUARTILE.INC(Data_Cleaned!Q2:Q1471,1) -> 2 | I21: =_xlfn.QUARTILE.INC(Data_Cleaned!Q2:Q1471,3) -> 4 | M21: =Data_Cleaned!B21 -> No | N21: =Data_Cleaned!S21 -> 3944 | P21: 5 | Q21: 4963 | R21: 0 | S21: 1232
A22: EnvironmentSatisfaction | B22: =COUNT(Data_Cleaned!K2:K1471) -> 1470 | C22: =AVERAGE(Data_Cleaned!K2:K1471) -> 2.7272109 | D22: =MEDIAN(Data_Cleaned!K2:K1471) -> 3 | E22: =_xlfn.STDEV.S(Data_Cleaned!K2:K1471) -> 1.0894667 | F22: =MIN(Data_Cleaned!K2:K1471) -> 1 | G22: =MAX(Data_Cleaned!K2:K1471) -> 4 | H22: =_xlfn.QUARTILE.INC(Data_Cleaned!K2:K1471,1) -> 2 | I22: =_xlfn.QUARTILE.INC(Data_Cleaned!K2:K1471,3) -> 4 | M22: =Data_Cleaned!B22 -> No | N22: =Data_Cleaned!S22 -> 4011 | P22: 7 | Q22: 6172 | R22: 14 | S22: 19094
A23: WorkLifeBalance | B23: =COUNT(Data_Cleaned!AE2:AE1471) -> 1470 | C23: =AVERAGE(Data_Cleaned!AE2:AE1471) -> 2.7612245 | D23: =MEDIAN(Data_Cleaned!AE2:AE1471) -> 3 | E23: =_xlfn.STDEV.S(Data_Cleaned!AE2:AE1471) -> 0.70647583 | F23: =MIN(Data_Cleaned!AE2:AE1471) -> 1 | G23: =MAX(Data_Cleaned!AE2:AE1471) -> 4 | H23: =_xlfn.QUARTILE.INC(Data_Cleaned!AE2:AE1471,1) -> 2 | I23: =_xlfn.QUARTILE.INC(Data_Cleaned!AE2:AE1471,3) -> 3 | M23: =Data_Cleaned!B23 -> Yes | N23: =Data_Cleaned!S23 -> 3407 | P23: 40 | Q23: 10312 | R23: 9 | S23: 6825
M24: =Data_Cleaned!B24 -> No | N24: =Data_Cleaned!S24 -> 11994 | P24: 0 | Q24: 1675 | R24: 22 | S24: 10248
M25: =Data_Cleaned!B25 -> No | N25: =Data_Cleaned!S25 -> 1232 | P25: 2 | Q25: 4559 | R25: 2 | S25: 18947
A26: 3. MISSING VALUE ANALYSIS (post-cleaning) | M26: =Data_Cleaned!B26 -> Yes | N26: =Data_Cleaned!S26 -> 2960 | P26: 4 | Q26: 10650 | R26: 1 | S26: 2496
A27: Blank cells across all 35 base columns (Data_Cleaned!A2:AI1471) | B27: {=SUMPRODUCT(--(Data_Cleaned!A2:AI1471=""))} -> 0 | M27: =Data_Cleaned!B27 -> No | N27: =Data_Cleaned!S27 -> 19094 | P27: 5 | Q27: 4200 | R27: 4 | S27: 6465
A28: Interpretation: after imputation, the cleaned dataset has zero remaining blanks — confirmed by the formula above. | M28: =Data_Cleaned!B28 -> Yes | N28: =Data_Cleaned!S28 -> 3919 | P28: 0 | Q28: 2325 | R28: 10 | S28: 2206
M29: =Data_Cleaned!B29 -> No | N29: =Data_Cleaned!S29 -> 6825 | P29: 1 | Q29: 1102 | R29: 5 | S29: 2645
A30: 4. TARGET VARIABLE ANALYSIS — ATTRITION | M30: =Data_Cleaned!B30 -> No | N30: =Data_Cleaned!S30 -> 10248 | P30: 4 | Q30: 3140 | R30: 2 | S30: 2014
A31: Employees who left (Attrition = Yes) | B31: =COUNTIF(Data_Cleaned!B2:B1471,"Yes") -> 237 | M31: =Data_Cleaned!B31 -> No | N31: =Data_Cleaned!S31 -> 18947 | P31: 1 | Q31: 5916 | R31: 1 | S31: 3419
A32: Employees who stayed (Attrition = No) | B32: =COUNTIF(Data_Cleaned!B2:B1471,"No") -> 1233 | M32: =Data_Cleaned!B32 -> No | N32: =Data_Cleaned!S32 -> 2496 | P32: 1 | Q32: 6673 | R32: 5 | S32: 5376
A33: Overall attrition rate | B33: =B31/(B31+B32) -> 0.16122449 | M33: =Data_Cleaned!B33 -> No | N33: =Data_Cleaned!S33 -> 6465 | P33: 10 | Q33: 7639 | R33: 1 | S33: 1951
A34: Class balance implication: the target is imbalanced (~16% positive class), so model evaluation should rely on Precision/Recall/F1/ROC-AUC rather than accuracy alone, and class weighting should be considered during training. | M34: =Data_Cleaned!B34 -> No | N34: =Data_Cleaned!S34 -> 2206 | P34: 14 | Q34: 10400 | R34: 1 | S34: 2341
M35: =Data_Cleaned!B35 -> Yes | N35: =Data_Cleaned!S35 -> 2086 | P35: 5 | Q35: 2657 | R35: 9 | S35: 8726
A36: 5. CATEGORY COMPARISONS — ATTRITION RATE BY SEGMENT | M36: =Data_Cleaned!B36 -> Yes | N36: =Data_Cleaned!S36 -> 2293 | P36: 6 | Q36: 6696 | R36: 12 | S36: 4011
M37: =Data_Cleaned!B37 -> No | N37: =Data_Cleaned!S37 -> 2645 | P37: 6 | Q37: 2058 | R37: 9 | S37: 4568
A38: By Department | E38: By OverTime | I38: By Gender | M38: =Data_Cleaned!B38 -> Yes | N38: =Data_Cleaned!S38 -> 2683 | P38: 4 | Q38: 2389 | R38: 1 | S38: 3022
A39: Department | B39: Headcount | C39: Attrition Rate | E39: OverTime | F39: Headcount | G39: Attrition Rate | I39: Gender | J39: Headcount | K39: Attrition Rate | M39: =Data_Cleaned!B39 -> No | N39: =Data_Cleaned!S39 -> 2014 | P39: 5 | Q39: 2436 | R39: 9 | S39: 5772
A40: Sales | B40: =COUNTIF(Data_Cleaned!$E$2:$E$1471,A40) -> 445 | C40: =AVERAGEIFS(Data_Cleaned!$AJ$2:$AJ$1471,Data_Cleaned!$E$2:$E$1471,A40) -> 0.20898876 | E40: Yes | F40: =COUNTIF(Data_Cleaned!$W$2:$W$1471,E40) -> 417 | G40: =AVERAGEIFS(Data_Cleaned!$AJ$2:$AJ$1471,Data_Cleaned!$W$2:$W$1471,E40) -> 0.30455635 | I40: Male | J40: =COUNTIF(Data_Cleaned!$L$2:$L$1471,I40) -> 882 | K40: =AVERAGEIFS(Data_Cleaned!$AJ$2:$AJ$1471,Data_Cleaned!$L$2:$L$1471,I40) -> 0.16893424 | M40: =Data_Cleaned!B40 -> No | N40: =Data_Cleaned!S40 -> 3419 | P40: 9 | Q40: 2707 | R40: 1 | S40: 2269
A41: Research & Development | B41: =COUNTIF(Data_Cleaned!$E$2:$E$1471,A41) -> 962 | C41: =AVERAGEIFS(Data_Cleaned!$AJ$2:$AJ$1471,Data_Cleaned!$E$2:$E$1471,A41) -> 0.13825364 | E41: No | F41: =COUNTIF(Data_Cleaned!$W$2:$W$1471,E41) -> 1053 | G41: =AVERAGEIFS(Data_Cleaned!$AJ$2:$AJ$1471,Data_Cleaned!$W$2:$W$1471,E41) -> 0.10446344 | I41: Female | J41: =COUNTIF(Data_Cleaned!$L$2:$L$1471,I41) -> 588 | K41: =AVERAGEIFS(Data_Cleaned!$AJ$2:$AJ$1471,Data_Cleaned!$L$2:$L$1471,I41) -> 0.14965986 | M41: =Data_Cleaned!B41 -> No | N41: =Data_Cleaned!S41 -> 5376 | P41: 3 | Q41: 3730 | R41: 4 | S41: 5454
A42: Human Resources | B42: =COUNTIF(Data_Cleaned!$E$2:$E$1471,A42) -> 63 | C42: =AVERAGEIFS(Data_Cleaned!$AJ$2:$AJ$1471,Data_Cleaned!$E$2:$E$1471,A42) -> 0.17460317 | M42: =Data_Cleaned!B42 -> No | N42: =Data_Cleaned!S42 -> 1951 | P42: 1 | Q42: 10048 | R42: 4 | S42: 9884
M43: =Data_Cleaned!B43 -> No | N43: =Data_Cleaned!S43 -> 2341 | P43: 5 | Q43: 3479 | R43: 2 | S43: 4157
A44: By Marital Status | E44: By Age Group | I44: By Income Band | M44: =Data_Cleaned!B44 -> Yes | N44: =Data_Cleaned!S44 -> 2293 | P44: 0 | Q44: 3485 | R44: 15 | S44: 5993
A45: MaritalStatus | B45: Headcount | C45: Attrition Rate | E45: AgeGroup | F45: Headcount | G45: Attrition Rate | I45: IncomeBand | J45: Headcount | K45: Attrition Rate | M45: =Data_Cleaned!B45 -> No | N45: =Data_Cleaned!S45 -> 8726 | P45: 10 | Q45: 11849 | R45: 9 | S45: 9069
A46: Single | B46: =COUNTIF(Data_Cleaned!$R$2:$R$1471,A46) -> 468 | C46: =AVERAGEIFS(Data_Cleaned!$AJ$2:$AJ$1471,Data_Cleaned!$R$2:$R$1471,A46) -> 0.25641026 | E46: Under 30 | F46: =COUNTIF(Data_Cleaned!$AP$2:$AP$1471,E46) -> 327 | G46: =AVERAGEIFS(Data_Cleaned!$AJ$2:$AJ$1471,Data_Cleaned!$AP$2:$AP$1471,E46) -> 0.27828746 | I46: Low | J46: =COUNTIF(Data_Cleaned!$AQ$2:$AQ$1471,I46) -> 368 | K46: =AVERAGEIFS(Data_Cleaned!$AJ$2:$AJ$1471,Data_Cleaned!$AQ$2:$AQ$1471,I46) -> 0.29076087 | M46: =Data_Cleaned!B46 -> No | N46: =Data_Cleaned!S46 -> 4011 | P46: 1 | Q46: 3161 | R46: 2 | S46: 4014
A47: Married | B47: =COUNTIF(Data_Cleaned!$R$2:$R$1471,A47) -> 675 | C47: =AVERAGEIFS(Data_Cleaned!$AJ$2:$AJ$1471,Data_Cleaned!$R$2:$R$1471,A47) -> 0.12444444 | E47: 30-39 | F47: =COUNTIF(Data_Cleaned!$AP$2:$AP$1471,E47) -> 624 | G47: =AVERAGEIFS(Data_Cleaned!$AJ$2:$AJ$1471,Data_Cleaned!$AP$2:$AP$1471,E47) -> 0.14423077 | I47: Medium | J47: =COUNTIF(Data_Cleaned!$AQ$2:$AQ$1471,I47) -> 367 | K47: =AVERAGEIFS(Data_Cleaned!$AJ$2:$AJ$1471,Data_Cleaned!$AQ$2:$AQ$1471,I47) -> 0.14441417 | M47: =Data_Cleaned!B47 -> Yes | N47: =Data_Cleaned!S47 -> 19545 | P47: 3 | Q47: 2373 | R47: 7 | S47: 5915
A48: Divorced | B48: =COUNTIF(Data_Cleaned!$R$2:$R$1471,A48) -> 327 | C48: =AVERAGEIFS(Data_Cleaned!$AJ$2:$AJ$1471,Data_Cleaned!$R$2:$R$1471,A48) -> 0.10091743 | E48: 40-49 | F48: =COUNTIF(Data_Cleaned!$AP$2:$AP$1471,E48) -> 348 | G48: =AVERAGEIFS(Data_Cleaned!$AJ$2:$AJ$1471,Data_Cleaned!$AP$2:$AP$1471,E48) -> 0.097701149 | I48: High | J48: =COUNTIF(Data_Cleaned!$AQ$2:$AQ$1471,I48) -> 367 | K48: =AVERAGEIFS(Data_Cleaned!$AJ$2:$AJ$1471,Data_Cleaned!$AQ$2:$AQ$1471,I48) -> 0.10626703 | M48: =Data_Cleaned!B48 -> No | N48: =Data_Cleaned!S48 -> 4568 | P48: 8 | Q48: 5828 | R48: 7 | S48: 5993
E49: 50+ | F49: =COUNTIF(Data_Cleaned!$AP$2:$AP$1471,E49) -> 171 | G49: =AVERAGEIFS(Data_Cleaned!$AJ$2:$AJ$1471,Data_Cleaned!$AP$2:$AP$1471,E49) -> 0.12865497 | I49: Very High | J49: =COUNTIF(Data_Cleaned!$AQ$2:$AQ$1471,I49) -> 368 | K49: =AVERAGEIFS(Data_Cleaned!$AJ$2:$AJ$1471,Data_Cleaned!$AQ$2:$AQ$1471,I49) -> 0.10326087 | M49: =Data_Cleaned!B49 -> No | N49: =Data_Cleaned!S49 -> 3022 | P49: 0 | Q49: 1420 | R49: 9 | S49: 6162
M50: =Data_Cleaned!B50 -> No | N50: =Data_Cleaned!S50 -> 5772 | P50: 8 | Q50: 4941 | R50: 10 | S50: 2406
A51: By Job Role | M51: =Data_Cleaned!B51 -> No | N51: =Data_Cleaned!S51 -> 2269 | P51: 3 | Q51: 3464 | R51: 27 | S51: 18740
A52: JobRole | B52: Headcount | C52: Attrition Rate | M52: =Data_Cleaned!B52 -> Yes | N52: =Data_Cleaned!S52 -> 5381 | P52: 1 | Q52: 5238 | R52: 21 | S52: 7637
A53: Sales Executive | B53: =COUNTIF(Data_Cleaned!$P$2:$P$1471,A53) -> 326 | C53: =AVERAGEIFS(Data_Cleaned!$AJ$2:$AJ$1471,Data_Cleaned!$P$2:$P$1471,A53) -> 0.17484663 | M53: =Data_Cleaned!B53 -> Yes | N53: =Data_Cleaned!S53 -> 3441 | P53: 7 | Q53: 2119 | R53: 17 | S53: 10096
A54: Research Scientist | B54: =COUNTIF(Data_Cleaned!$P$2:$P$1471,A54) -> 292 | C54: =AVERAGEIFS(Data_Cleaned!$AJ$2:$AJ$1471,Data_Cleaned!$P$2:$P$1471,A54) -> 0.1609589 | M54: =Data_Cleaned!B54 -> No | N54: =Data_Cleaned!S54 -> 5454 | P54: 3 | Q54: 2174 | R54: 5 | S54: 4200
A55: Laboratory Technician | B55: =COUNTIF(Data_Cleaned!$P$2:$P$1471,A55) -> 259 | C55: =AVERAGEIFS(Data_Cleaned!$AJ$2:$AJ$1471,Data_Cleaned!$P$2:$P$1471,A55) -> 0.23938224 | M55: =Data_Cleaned!B55 -> No | N55: =Data_Cleaned!S55 -> 9884 | P55: 1 | Q55: 2851 | R55: 6 | S55: 6499
A56: Manufacturing Director | B56: =COUNTIF(Data_Cleaned!$P$2:$P$1471,A56) -> 145 | C56: =AVERAGEIFS(Data_Cleaned!$AJ$2:$AJ$1471,Data_Cleaned!$P$2:$P$1471,A56) -> 0.068965517 | M56: =Data_Cleaned!B56 -> No | N56: =Data_Cleaned!S56 -> 4157 | P56: 8 | Q56: 9355 | R56: 1 | S56: 9724
A57: Healthcare Representative | B57: =COUNTIF(Data_Cleaned!$P$2:$P$1471,A57) -> 131 | C57: =AVERAGEIFS(Data_Cleaned!$AJ$2:$AJ$1471,Data_Cleaned!$P$2:$P$1471,A57) -> 0.06870229 | M57: =Data_Cleaned!B57 -> No | N57: =Data_Cleaned!S57 -> 5993 | P57: 6 | Q57: 6380 | R57: 3 | S57: 2194
A58: Manager | B58: =COUNTIF(Data_Cleaned!$P$2:$P$1471,A58) -> 102 | C58: =AVERAGEIFS(Data_Cleaned!$AJ$2:$AJ$1471,Data_Cleaned!$P$2:$P$1471,A58) -> 0.049019608 | M58: =Data_Cleaned!B58 -> No | N58: =Data_Cleaned!S58 -> 9069 | P58: 1 | Q58: 2716 | R58: 4 | S58: 5473
A59: Sales Representative | B59: =COUNTIF(Data_Cleaned!$P$2:$P$1471,A59) -> 83 | C59: =AVERAGEIFS(Data_Cleaned!$AJ$2:$AJ$1471,Data_Cleaned!$P$2:$P$1471,A59) -> 0.39759036 | M59: =Data_Cleaned!B59 -> No | N59: =Data_Cleaned!S59 -> 4014 | P59: 5 | Q59: 5304 | R59: 5 | S59: 2703
A60: Research Director | B60: =COUNTIF(Data_Cleaned!$P$2:$P$1471,A60) -> 80 | C60: =AVERAGEIFS(Data_Cleaned!$AJ$2:$AJ$1471,Data_Cleaned!$P$2:$P$1471,A60) -> 0.025 | M60: =Data_Cleaned!B60 -> No | N60: =Data_Cleaned!S60 -> 5915 | P60: 6 | Q60: 3102 | R60: 1 | S60: 2501
A61: Human Resources | B61: =COUNTIF(Data_Cleaned!$P$2:$P$1471,A61) -> 52 | C61: =AVERAGEIFS(Data_Cleaned!$AJ$2:$AJ$1471,Data_Cleaned!$P$2:$P$1471,A61) -> 0.23076923 | M61: =Data_Cleaned!B61 -> No | N61: =Data_Cleaned!S61 -> 5993 | P61: 1 | Q61: 2285 | R61: 10 | S61: 6220
M62: =Data_Cleaned!B62 -> No | N62: =Data_Cleaned!S62 -> 6162 | P62: 2 | Q62: 4031 | R62: 1 | S62: 3038
M63: =Data_Cleaned!B63 -> No | N63: =Data_Cleaned!S63 -> 2406 | P63: 5 | Q63: 3202 | R63: 11 | S63: 6500
A64: 6. CORRELATION ANALYSIS — NUMERIC VARIABLES vs ATTRITION | M64: =Data_Cleaned!B64 -> No | N64: =Data_Cleaned!S64 -> 18740 | P64: 2 | Q64: 2351 | R64: 15 | S64: 4312
A65: Variable | B65: Correlation with Attrition_Flag | M65: =Data_Cleaned!B65 -> No | N65: =Data_Cleaned!S65 -> 7637 | P65: 2 | Q65: 2546 | R65: 0 | S65: 13245
A66: OverTime_Flag | B66: =CORREL(Data_Cleaned!AK2:AK1471,Data_Cleaned!AJ2:AJ1471) -> 0.24527779 | M66: =Data_Cleaned!B66 -> No | N66: =Data_Cleaned!S66 -> 10096 | P66: 1 | Q66: 2564 | R66: 5 | S66: 13664
A67: MonthlyIncome | B67: =CORREL(Data_Cleaned!S2:S1471,Data_Cleaned!AJ2:AJ1471) -> -0.15841424 | M67: =Data_Cleaned!B67 -> No | N67: =Data_Cleaned!S67 -> 4200 | P67: 7 | Q67: 13610 | R67: 4 | S67: 5021
A68: Age | B68: =CORREL(Data_Cleaned!A2:A1471,Data_Cleaned!AJ2:AJ1471) -> -0.16210415 | M68: =Data_Cleaned!B68 -> No | N68: =Data_Cleaned!S68 -> 6499 | P68: 4 | Q68: 3408 | R68: 10 | S68: 5126
A69: TotalWorkingYears | B69: =CORREL(Data_Cleaned!AC2:AC1471,Data_Cleaned!AJ2:AJ1471) -> -0.16747402 | M69: =Data_Cleaned!B69 -> No | N69: =Data_Cleaned!S69 -> 9724 | P69: 1 | Q69: 9824 | R69: 6 | S69: 2859
A70: YearsAtCompany | B70: =CORREL(Data_Cleaned!AF2:AF1471,Data_Cleaned!AJ2:AJ1471) -> -0.13439221 | M70: =Data_Cleaned!B70 -> No | N70: =Data_Cleaned!S70 -> 2194 | P70: 3 | Q70: 9950 | R70: 1 | S70: 10239
A71: YearsSinceLastPromotion | B71: =CORREL(Data_Cleaned!AH2:AH1471,Data_Cleaned!AJ2:AJ1471) -> -0.033018775 | M71: =Data_Cleaned!B71 -> Yes | N71: =Data_Cleaned!S71 -> 3388 | P71: 2 | Q71: 3894 | R71: 13 | S71: 5329
A72: JobSatisfaction | B72: =CORREL(Data_Cleaned!Q2:Q1471,Data_Cleaned!AJ2:AJ1471) -> -0.10348113 | M72: =Data_Cleaned!B72 -> No | N72: =Data_Cleaned!S72 -> 5473 | P72: 7 | Q72: 2741 | R72: 5 | S72: 4325
A73: EnvironmentSatisfaction | B73: =CORREL(Data_Cleaned!K2:K1471,Data_Cleaned!AJ2:AJ1471) -> -0.1059028 | M73: =Data_Cleaned!B73 -> No | N73: =Data_Cleaned!S73 -> 2703 | P73: 0 | Q73: 1878 | R73: 6 | S73: 7260
A74: WorkLifeBalance | B74: =CORREL(Data_Cleaned!AE2:AE1471,Data_Cleaned!AJ2:AJ1471) -> -0.063939047 | M74: =Data_Cleaned!B74 -> No | N74: =Data_Cleaned!S74 -> 2501 | P74: 1 | Q74: 2340 | R74: 0 | S74: 2322
A75: DistanceFromHome | B75: =CORREL(Data_Cleaned!F2:F1471,Data_Cleaned!AJ2:AJ1471) -> 0.077568387 | M75: =Data_Cleaned!B75 -> No | N75: =Data_Cleaned!S75 -> 6220 | P75: 4 | Q75: 4707 | R75: 4 | S75: 2075
A76: NumCompaniesWorked | B76: =CORREL(Data_Cleaned!U2:U1471,Data_Cleaned!AJ2:AJ1471) -> 0.043270865 | M76: =Data_Cleaned!B76 -> No | N76: =Data_Cleaned!S76 -> 3038 | P76: 6 | Q76: 2886 | R76: 11 | S76: 4152
A77: StockOptionLevel | B77: =CORREL(Data_Cleaned!AB2:AB1471,Data_Cleaned!AJ2:AJ1471) -> -0.13714492 | M77: =Data_Cleaned!B77 -> No | N77: =Data_Cleaned!S77 -> 6500 | P77: 1 | Q77: 2033 | R77: 22 | S77: 13503
A78: PercentSalaryHike | B78: =CORREL(Data_Cleaned!X2:X1471,Data_Cleaned!AJ2:AJ1471) -> -0.012834119 | M78: =Data_Cleaned!B78 -> No | N78: =Data_Cleaned!S78 -> 4312 | P78: 3 | Q78: 4233 | R78: 10 | S78: 5441
A79: TrainingTimesLastYear | B79: =CORREL(Data_Cleaned!AD2:AD1471,Data_Cleaned!AJ2:AJ1471) -> -0.059477799 | M79: =Data_Cleaned!B79 -> No | N79: =Data_Cleaned!S79 -> 13245 | P79: 4 | Q79: 3041 | R79: 11 | S79: 5209
M80: =Data_Cleaned!B80 -> No | N80: =Data_Cleaned!S80 -> 13664 | P80: 1 | Q80: 4286 | R80: 10 | S80: 10673
A81: 7. GROUPING & AGGREGATION — AVG MONTHLY INCOME BY DEPARTMENT & ATTRITION | M81: =Data_Cleaned!B81 -> No | N81: =Data_Cleaned!S81 -> 5021 | P81: 1 | Q81: 1009 | R81: 11 | S81: 5010
A82: Department | B82: Avg Income (Stayed) | C82: Avg Income (Left) | D82: Income Gap | M82: =Data_Cleaned!B82 -> No | N82: =Data_Cleaned!S82 -> 5126 | P82: 10 | Q82: 3348 | R82: 4 | S82: 13549
A83: Sales | B83: =AVERAGEIFS(Data_Cleaned!$S$2:$S$1471,Data_Cleaned!$E$2:$E$1471,$A83,Data_Cleaned!$B$2:$B$1471,"No") -> 7213.3153 | C83: =AVERAGEIFS(Data_Cleaned!$S$2:$S$1471,Data_Cleaned!$E$2:$E$1471,$A83,Data_Cleaned!$B$2:$B$1471,"Yes") -> 5867.2151 | D83: =B83-C83 -> 1346.1003 | M83: =Data_Cleaned!B83 -> No | N83: =Data_Cleaned!S83 -> 2859 | P83: 2 | Q83: 4577 | R83: 3 | S83: 4999
A84: Research & Development | B84: =AVERAGEIFS(Data_Cleaned!$S$2:$S$1471,Data_Cleaned!$E$2:$E$1471,$A84,Data_Cleaned!$B$2:$B$1471,"No") -> 6616.4403 | C84: =AVERAGEIFS(Data_Cleaned!$S$2:$S$1471,Data_Cleaned!$E$2:$E$1471,$A84,Data_Cleaned!$B$2:$B$1471,"Yes") -> 4117.8947 | D84: =B84-C84 -> 2498.5456 | M84: =Data_Cleaned!B84 -> No | N84: =Data_Cleaned!S84 -> 10239 | P84: 4 | Q84: 6796 | R84: 5 | S84: 4221
A85: Human Resources | B85: =AVERAGEIFS(Data_Cleaned!$S$2:$S$1471,Data_Cleaned!$E$2:$E$1471,$A85,Data_Cleaned!$B$2:$B$1471,"No") -> 7326.2885 | C85: =AVERAGEIFS(Data_Cleaned!$S$2:$S$1471,Data_Cleaned!$E$2:$E$1471,$A85,Data_Cleaned!$B$2:$B$1471,"Yes") -> 3865.0909 | D85: =B85-C85 -> 3461.1976 | M85: =Data_Cleaned!B85 -> No | N85: =Data_Cleaned!S85 -> 5329 | P85: 7 | Q85: 2216 | R85: 37 | S85: 13872
M86: =Data_Cleaned!B86 -> No | N86: =Data_Cleaned!S86 -> 4325 | P86: 2 | Q86: 2759 | R86: 3 | S86: 2042
A87: 8. TREND ANALYSIS — ATTRITION RATE BY TENURE | M87: =Data_Cleaned!B87 -> No | N87: =Data_Cleaned!S87 -> 7260 | P87: 10 | Q87: 2686 | R87: 1 | S87: 2956
A88: YearsAtCompany Bucket | B88: Headcount | C88: Attrition Rate | M88: =Data_Cleaned!B88 -> No | N88: =Data_Cleaned!S88 -> 2322 | P88: 5 | Q88: 6397 | R88: 16 | S88: 4809
A89: 0-2 yrs | B89: =COUNTIFS(Data_Cleaned!$AF$2:$AF$1471,">=0",Data_Cleaned!$AF$2:$AF$1471,"<=2") -> 342 | C89: =AVERAGEIFS(Data_Cleaned!$AJ$2:$AJ$1471,Data_Cleaned!$AF$2:$AF$1471,">=0",Data_Cleaned!$AF$2:$AF$1471,"<=2") -> 0.29824561 | M89: =Data_Cleaned!B89 -> No | N89: =Data_Cleaned!S89 -> 2075 | P89: 5 | Q89: 19859 | R89: 1 | S89: 5163
A90: 3-5 yrs | B90: =COUNTIFS(Data_Cleaned!$AF$2:$AF$1471,">=3",Data_Cleaned!$AF$2:$AF$1471,"<=5") -> 434 | C90: =AVERAGEIFS(Data_Cleaned!$AJ$2:$AJ$1471,Data_Cleaned!$AF$2:$AF$1471,">=3",Data_Cleaned!$AF$2:$AF$1471,"<=5") -> 0.13824885 | M90: =Data_Cleaned!B90 -> No | N90: =Data_Cleaned!S90 -> 4152 | P90: 4 | Q90: 5326 | R90: 3 | S90: 18844
A91: 6-10 yrs | B91: =COUNTIFS(Data_Cleaned!$AF$2:$AF$1471,">=6",Data_Cleaned!$AF$2:$AF$1471,"<=10") -> 448 | C91: =AVERAGEIFS(Data_Cleaned!$AJ$2:$AJ$1471,Data_Cleaned!$AF$2:$AF$1471,">=6",Data_Cleaned!$AF$2:$AF$1471,"<=10") -> 0.12276786 | M91: =Data_Cleaned!B91 -> Yes | N91: =Data_Cleaned!S91 -> 9619 | P91: 0 | Q91: 1601 | R91: 8 | S91: 18172
A92: 11+ yrs | B92: =COUNTIFS(Data_Cleaned!$AF$2:$AF$1471,">=11") -> 246 | C92: =AVERAGEIFS(Data_Cleaned!$AJ$2:$AJ$1471,Data_Cleaned!$AF$2:$AF$1471,">=11") -> 0.081300813 | M92: =Data_Cleaned!B92 -> No | N92: =Data_Cleaned!S92 -> 13503 | P92: 1 | Q92: 2319 | R92: 2 | S92: 2889
M93: =Data_Cleaned!B93 -> No | N93: =Data_Cleaned!S93 -> 5441 | P93: 3 | Q93: 5324 | R93: 0 | S93: 2871
M94: =Data_Cleaned!B94 -> No | N94: =Data_Cleaned!S94 -> 5209 | P94: 31 | Q94: 19246 | R94: 13 | S94: 7484
M95: =Data_Cleaned!B95 -> No | N95: =Data_Cleaned!S95 -> 10673 | P95: 2 | Q95: 4382 | R95: 5 | S95: 17328
M96: =Data_Cleaned!B96 -> No | N96: =Data_Cleaned!S96 -> 5010 | P96: 9 | Q96: 7654 | R96: 5 | S96: 2774
M97: =Data_Cleaned!B97 -> No | N97: =Data_Cleaned!S97 -> 13549 | P97: 9 | Q97: 5160 | R97: 1 | S97: 4505
M98: =Data_Cleaned!B98 -> No | N98: =Data_Cleaned!S98 -> 4999 | P98: 8 | Q98: 2366 | R98: 5 | S98: 7428
M99: =Data_Cleaned!B99 -> No | N99: =Data_Cleaned!S99 -> 4221 | P99: 10 | Q99: 2022 | R99: 11 | S99: 11631
M100: =Data_Cleaned!B100 -> No | N100: =Data_Cleaned!S100 -> 13872 | P100: 3 | Q100: 2800 | R100: 9 | S100: 9738
...

Sheet ML_Model
A1: MACHINE LEARNING MODEL — EMPLOYEE ATTRITION PREDICTION
A3: PREDICTION PROBLEM
A4: Binary classification: predict Attrition (Yes/No) for each employee using 33 engineered features (17 numeric drivers, OverTime and Gender flags, and one-hot encoded Department, Marital Status, Business Travel and Job Role). This lets HR score every active employee with a leave-risk probability rather than reacting only after a resignation is submitted.
A6: WHY ATTRITION WAS CHOSEN AS TARGET
A7: It is the only outcome in the dataset that is directly actionable (HR can intervene per employee), financially material (turnover cost), and richly explained by the available numeric and categorical predictors, as confirmed in the EDA correlation analysis (EDA_Summary tab).
A9: METHODOLOGY
A10: Data source: Data_Cleaned (1,470 employees). Split: stratified 80/20 train/test (seeded for reproducibility) so the ~16% attrition rate is preserved in both sets. Numeric features standardized (z-score); categorical variables one-hot encoded with a baseline category dropped. Three models trained: Logistic Regression (L2-regularized, gradient descent), Decision Tree (CART, Gini impurity, max depth 5), and Random Forest (15-tree bootstrap ensemble, max depth 6, sqrt(features) per split).
A12: Training set | B12: 1176 | C12: (190 attrition cases, 16.2%)
A13: Test set | B13: 294 | C13: (47 attrition cases, 16.0%)
A15: MODEL COMPARISON — TEST SET PERFORMANCE
A16: Model | B16: Accuracy | C16: Precision | D16: Recall | E16: F1 Score | F16: ROC-AUC | G16: TP | H16: FP | I16: TN | J16: FN
A17: Logistic Regression | B17: 0.8707 | C17: 0.7368 | D17: 0.2979 | E17: 0.4242 | F17: 0.7766 | G17: 14 | H17: 5 | I17: 242 | J17: 33
A18: Decision Tree | B18: 0.8367 | C18: 0.4815 | D18: 0.2766 | E18: 0.3514 | F18: 0.6938 | G18: 13 | H18: 14 | I18: 233 | J18: 34
A19: Random Forest | B19: 0.8537 | C19: 0.75 | D19: 0.1277 | E19: 0.2182 | F19: 0.7921 | G19: 6 | H19: 2 | I19: 245 | J19: 41
A21: BEST MODEL: Logistic Regression
A22: Selection rationale: Random Forest has the highest ROC-AUC (0.792) and precision, but its recall (12.8%) means it misses 41 of 47 employees who actually left — unacceptable for a retention-flagging tool where the cost of missing a true leaver outweighs the cost of a false alarm. Logistic Regression gives the best balance (F1=0.424) between catching real attrition risk (Recall 29.8%) and not over-alerting HR (Precision 73.7%), while also remaining fully interpretable — each coefficient has a clear business meaning, which matters for HR adoption and trust.
A25: FEATURE IMPORTANCE (top 8 per model)
A26: Logistic Regression (|coef|) | B26: Weight | D26: Decision Tree | E26: Importance | G26: Random Forest | H26: Importance
A27: OverTime_Flag | B27: 1.299 | D27: JobLevel | E27: 0.1751 | G27: OverTime_Flag | H27: 0.1317
A28: MaritalStatus_Divorced | B28: 0.666 | D28: OverTime_Flag | E28: 0.1744 | G28: Age | H28: 0.1011
A29: Department_R&D | B29: 0.649 | D29: StockOptionLevel | E29: 0.1149 | G29: MonthlyIncome | H29: 0.0892
A30: JobRole_Lab Technician | B30: 0.445 | D30: MonthlyIncome | E30: 0.0774 | G30: DistanceFromHome | H30: 0.0547
A31: MaritalStatus_Married | B31: 0.412 | D31: DailyRate | E31: 0.0724 | G31: TotalWorkingYears | H31: 0.0536
A32: JobRole_Research Scientist | B32: 0.387 | D32: TotalWorkingYears | E32: 0.0568 | G32: DailyRate | H32: 0.0513
A33: YearsSinceLastPromotion | B33: 0.387 | D33: TrainingTimesLastYear | E33: 0.0466 | G33: NumCompaniesWorked | H33: 0.0507
A34: BusinessTravel_Non-Travel | B34: 0.38 | D34: Department_R&D | E34: 0.0451 | G34: JobInvolvement | H34: 0.0405
A36: BUSINESS INTERPRETATION OF FEATURE IMPORTANCE
A37: All three models independently rank OverTime as the #1 or #2 predictor of attrition — this is the most actionable and consistent signal in the data, corroborating the EDA finding that overtime employees leave at nearly 3x the rate of non-overtime employees. Compensation (MonthlyIncome, DailyRate), tenure/experience (TotalWorkingYears), and role/marital-status context also recur across models, but with less consistency — indicating they matter but are secondary to workload management.
A39: EVALUATION METRICS EXPLAINED (BUSINESS LANGUAGE)
A40: Accuracy: % of all employees correctly classified. Misleading here because 84% of employees stay anyway — a model that always predicts "stays" would score 84% accuracy while catching zero real leavers.
A41: Precision: of employees flagged as "at risk", what % actually left. High precision means HR's limited retention budget isn't wasted on false alarms.
A42: Recall: of employees who actually left, what % the model caught in advance. This is the metric that matters most for a proactive retention programme — missed leavers (false negatives) are the real business cost.
A43: F1 Score: harmonic mean of Precision and Recall — used here as the primary model-selection metric because it balances both concerns.
A44: ROC-AUC: the model's ability to rank at-risk employees above safe employees across all thresholds, independent of the 0.5 cutoff — useful for building a prioritized watch-list rather than a strict yes/no flag.
A46: EQUIVALENT PYTHON (SCIKIT-LEARN) IMPLEMENTATION
A47: from sklearn.model_selection import train_test_split from sklearn.preprocessing import StandardScaler from sklearn.linear_model import LogisticRegression from sklearn.tree import DecisionTreeClassifier from sklearn.ensemble import RandomForestClassifier from sklearn.metrics import accuracy_score, precision_score, recall_score, f1_score, roc_auc_score import pandas as pd df = pd.read_csv('HR_Employee_Attrition_Cleaned.csv') y = df['Attrition_Flag'] feature_cols = ['Age','MonthlyIncome','DistanceFromHome','TotalWorkingYears','YearsAtCompany', 'YearsInCurrentRole','YearsSinceLastPromotion','NumCompaniesWorked','PercentSalaryHike', 'TrainingTimesLastYear','JobSatisfaction','EnvironmentSatisfaction','WorkLifeBalance', 'JobInvolvement','StockOptionLevel','JobLevel','DailyRate','OverTime_Flag','Gender_Flag'] X = pd.get_dummies(df[feature_cols + ['Department','MaritalStatus','BusinessTravel','JobRole']], columns=['Department','MaritalStatus','BusinessTravel','JobRole'], drop_first=True) X_train, X_test, y_train, y_test = train_test_split(X, y, test_size=0.2, stratify=y, random_state=42) scaler = StandardScaler() num_cols = feature_cols[:17] X_train[num_cols] = scaler.fit_transform(X_train[num_cols]) X_test[num_cols] = scaler.transform(X_test[num_cols]) models = { 'Logistic Regression': LogisticRegression(C=1/0.005, max_iter=1000), 'Decision Tree': DecisionTreeClassifier(max_depth=5, min_samples_split=20, random_state=42), 'Random Forest': RandomForestClassifier(n_estimators=15, max_depth=6, min_samples_split=10, random_state=42) } results = {} for name, model in models.items(): model.fit(X_train, y_train) proba = model.predict_proba(X_test)[:, 1] pred = (proba >= 0.5).astype(int) results[name] = { 'accuracy': accuracy_score(y_test, pred), 'precision': precision_score(y_test, pred), 'recall': recall_score(y_test, pred), 'f1': f1_score(y_test, pred), 'roc_auc': roc_auc_score(y_test, proba) } results_df = pd.DataFrame(results).T print(results_df) # Feature importance import numpy as np coef_importance = pd.Series(np.abs(models['Logistic Regression'].coef_[0]), index=X_train.columns).sort_values(ascending=False) tree_importance = pd.Series(models['Random Forest'].feature_importances_, index=X_train.columns).sort_values(ascending=False)

Sheet Business_Insights
A1: BUSINESS INSIGHTS — HR EMPLOYEE ATTRITION
A3: # | B3: Observation | C3: Supporting Evidence | D3: Business Impact | E3: Recommendation
A4: 1 | B4: Overall attrition runs at 16.1% of headcount. | C4: ="EDA_Summary!B33 = "&TEXT(EDA_Summary!B33,"0.0%")&" (237 of 1,470 employees)" -> EDA_Summary!B33 = 16.1% (237 of 1,470 employees) | D4: At typical replacement costs (50-200% of salary), this represents a recurring seven-figure exposure across the workforce. | E4: Set a formal attrition-reduction target (e.g., <12% within 12 months) and track monthly via the KPI dashboard.
A5: 2 | B5: Overtime is the single strongest driver of attrition. | C5: EDA_Summary!G40:G41 — 30.5% attrition among OverTime=Yes vs 10.4% for OverTime=No; correlation r=0.245 (EDA_Summary!B66), also ranked #1 feature by both Logistic Regression and Random Forest (ML_Model!A27,A28). | D5: Chronic overtime is triple the risk factor for losing an employee compared to any other single variable measured. | E5: Audit teams/roles with sustained overtime; add headcount or redistribute workload rather than relying on extended hours.
A6: 3 | B6: Attrition risk is highest in the first two years and falls steadily with tenure. | C6: EDA_Summary!A89:C92 — 29.8% attrition at 0-2 years vs 8.1% at 11+ years. | D6: New hires are the most fragile cohort; losing them wastes the entire recruiting and onboarding investment before it pays back. | E6: Strengthen onboarding, assign mentors, and schedule structured check-ins at 30/60/90 days and 12 months.
A7: 4 | B7: Sales Representatives have by far the highest role-level attrition (39.8%). | C7: EDA_Summary!A59,C59. | D7: This single role drives a disproportionate share of total turnover cost and likely disrupts client relationships. | E7: Review Sales Representative compensation, quota structure and career-path clarity specifically, rather than a department-wide fix.
A8: 5 | B8: The Sales department attrition rate (20.9%) exceeds R&D (13.8%) and HR (17.5%). | C8: EDA_Summary!A40:C42. | D8: Sales' higher turnover concentrates replacement and training cost in the revenue-generating function. | E8: Prioritize the retention programme rollout in Sales before other departments.
A9: 6 | B9: Employees who leave are paid less, on average, than those who stay — in every department. | C9: EDA_Summary!A82:D85 — income gap ranges from $1,346/month (Sales) to $3,461/month (HR); overall correlation r=-0.158 (EDA_Summary!B67). | D9: Pay compression versus market/peers is a plausible push factor, especially pronounced in Human Resources. | E9: Benchmark HR and Sales pay bands against market data and consider targeted adjustments for tenured, high-performing staff.
A10: 7 | B10: Single employees leave at more than double the rate of married or divorced employees. | C10: EDA_Summary!A46:C48 — 25.6% (Single) vs 12.4% (Married) vs 10.1% (Divorced). | D10: Life-stage/stability factors correlate with retention; single employees may be more mobile or less anchored to the area. | E10: No policy change implied, but include marital-status-neutral engagement programmes (relocation flexibility, community-building) that address the likely underlying driver (geographic/social mobility).
A11: 8 | B11: Employees under 30 attrit at more than double the rate of employees 40+. | C11: EDA_Summary!E46:G49 — 27.8% (Under 30) vs 9.8% (40-49). | D11: Early-career staff represent both the highest churn risk and the largest future-leadership pipeline if retained. | E11: Build early-career retention paths: clear promotion timelines, mentorship, and stretch assignments within the first 3 years.
A12: 9 | B12: Low-income-band employees leave nearly 3x more often than very-high-income employees. | C12: EDA_Summary!I46:K49 — 29.1% (Low) vs 10.3% (Very High). | D12: Compensation at the lower band is a material retention risk, independent of department. | E12: Review minimum pay bands company-wide and consider a retention-focused adjustment for the bottom income quartile.
A13: 10 | B13: A Logistic Regression model can flag at-risk employees with 73.7% precision. | C13: ML_Model!C17 — Precision 73.7%, Recall 29.8%, F1 0.424, AUC 0.777 (ML_Model!B17:F17). | D13: Even an imperfect model lets HR focus limited retention budget on the employees statistically most likely to leave, rather than blanket spending. | E13: Operationalize the model as a monthly “attrition watch-list” for HR business partners, prioritizing high-probability, high-value employees.
A14: 11 | B14: 1.4% of the raw data (missing, duplicate, inconsistent, mistyped or outlier values) required cleaning before analysis was reliable. | C14: Cleaning_Log!A5:H10 — 40 missing values, 15 duplicate records, 21 inconsistent category labels, 10 type errors, 8 outliers, 2 scale errors identified and corrected. | D14: Without cleaning, attrition rates, income averages and model accuracy would all be measurably biased. | E14: Implement the source-system validation controls proposed in Cleaning_Log (dropdowns, uniqueness constraints, range checks) to prevent recurrence.

Sheet AI_Insights
A1: AI-ASSISTED OBSERVATIONS
A2: These observations were generated by pattern-scanning the correlation, segment and model-importance outputs already computed in EDA_Summary and ML_Model, then validated by checking whether the underlying numbers actually support the pattern (rather than accepting the pattern at face value).
A4: Category | B4: AI-Generated Insight | C4: How It Was Derived | D4: Validation Against Data | E4: Data Support Level
A5: Key Trend | B5: Attrition risk decays roughly monotonically with tenure — the relationship looks like a retention "survival curve" rather than a random pattern. | C5: Scanned the four tenure-bucket attrition rates for monotonic decline (each bucket lower than the previous). | D5: 29.8% → 13.8% → 12.3% → 8.1% across the four buckets (EDA_Summary!C89:C92) — strictly decreasing, confirming the pattern is real, not noise. | E5: Strongly supported
A6: Risk Factor | B6: Overtime is not just correlated with attrition but appears to be a compounding risk factor when combined with low tenure or low income. | C6: Compared OverTime's standalone correlation (r=0.245) against its rank as the top feature in two independent model types (Logistic Regression and Random Forest). | D6: OverTime_Flag is the #1-ranked feature in both Logistic Regression and Random Forest (ML_Model!A27,G27), which use completely different mathematics — agreement across model families is a stronger signal than either model alone. | E6: Strongly supported
A7: Risk Factor | B7: Role-specific dissatisfaction, not just department, drives some of the highest attrition (Sales Representative, Laboratory Technician). | C7: Compared department-level attrition rates against role-level rates within the same department to see if variance was hidden by aggregation. | D7: Sales dept. attrition is 20.9% overall, but Sales Representative alone is 39.8% vs Sales Executive 17.5% and Manager 4.9% (EDA_Summary!A53:C61) — department-level analysis alone would have masked this. | E7: Strongly supported
A8: Opportunity | B8: A meaningful share of attrition may be preventable at low cost through overtime and workload management rather than expensive compensation overhauls. | C8: Compared the effect size of OverTime (r=0.245, cheap to fix operationally) against MonthlyIncome (r=-0.158, expensive to fix). | D8: OverTime shows a larger effect size than income in both the correlation table and feature-importance rankings (EDA_Summary!B66:B67; ML_Model top features), suggesting workload redistribution could have outsized ROI versus blanket raises. | E8: Moderately supported — correlation, not causation; a controlled pilot is recommended before assuming causality.
A9: Employee Behavior Pattern | B9: Early-career, single, lower-income employees form a distinct "flight risk" cluster rather than three independent risk factors. | C9: Cross-checked whether Age, MaritalStatus and IncomeBand attrition effects overlap on the same demographic (early-career employees are disproportionately single and lower-paid by definition of tenure-linked pay scales). | D9: Under-30 (27.8%), Single (25.6%) and Low-income (29.1%) attrition rates are all far above the 16.1% baseline (EDA_Summary!E46,A46,I46) and describe an overlapping population, not three separate ones. | E9: Moderately supported — dataset does not allow a direct cross-tab of all three fields simultaneously without further segmentation analysis.
A10: Business Recommendation | B10: A rules-based early-warning flag (OverTime=Yes AND Tenure<=2 years) would likely outperform intuition-based manager judgment for prioritizing retention conversations. | C10: Combined the two strongest independent risk factors identified (OverTime and low tenure) into a simple compound business rule. | D10: Both factors are top-3 signals independently (EDA_Summary!G40, C89); combining the two highest-effect, low-cost-to-observe variables is a standard, defensible heuristic even without building the full ML pipeline. | E10: Supported as a heuristic; the Logistic Regression model (ML_Model tab) formalizes this same intuition with quantified probabilities and should be preferred where available.

Sheet KPIs
A1: KEY PERFORMANCE INDICATORS — HR ATTRITION
A3: KPI | B3: Definition | C3: Formula | D3: Actual | E3: Target | F3: Target Justification | G3: Status | H3: Business Interpretation
A4: Overall Attrition Rate | B4: % of total headcount that left during the period. | C4: Employees Left ÷ Total Employees | D4: =EDA_Summary!B33 -> 0.16122449 | E4: 0.12 | F4: Common HR industry benchmark for "healthy" voluntary turnover is 10-15%; 12% sets a stretch-but-achievable goal below the current rate. | G4: =IF(D4<=E4,"On/Above Target",IF(D4<=E4*1.15,"Near Target","Below Target")) -> Below Target | H4: Current attrition (16.1%) exceeds the target by ~4 points, confirming the retention programme is needed, not optional.
A5: OverTime Attrition Rate | B5: Attrition rate among employees who regularly work overtime — the highest-leverage segment identified in the analysis. | C5: Employees Left (OverTime=Yes) ÷ Employees (OverTime=Yes) | D5: =EDA_Summary!G40 -> 0.30455635 | E5: 0.2 | F5: Set to roughly match the overall-workforce target rate plus a margin, since overtime employees will likely always run somewhat higher risk; 20% would still be a large improvement from today. | G5: =IF(D5<=E5,"On/Above Target",IF(D5<=E5*1.15,"Near Target","Below Target")) -> Below Target | H5: At 30.5%, this segment is running 10+ points above target — the single most actionable KPI on this sheet given OverTime's #1 rank in feature importance.
A6: Early-Tenure Attrition Rate (0-2 yrs) | B6: Attrition rate among employees in their first two years — the highest-risk tenure window identified in EDA. | C6: Employees Left (Tenure 0-2 yrs) ÷ Employees (Tenure 0-2 yrs) | D6: =EDA_Summary!C89 -> 0.29824561 | E6: 0.2 | F6: New hires will always be somewhat more likely to leave during adjustment; 20% is an achievable reduction from the current 29.8% via stronger onboarding. | G6: =IF(D6<=E6,"On/Above Target",IF(D6<=E6*1.15,"Near Target","Below Target")) -> Below Target | H6: New-hire attrition is nearly 10 points above target, validating the onboarding-investment recommendation in Business_Insights.
A7: Retention-Model Precision | B7: Of employees the ML model flags as "at risk", the % who actually left — measures whether HR's retention budget would be well-targeted. | C7: True Positives ÷ (True Positives + False Positives), test set | D7: =ML_Model!C17 -> 0.7368 | E7: 0.7 | F7: 70% precision means at most 3 in 10 flagged employees are false alarms — an acceptable ratio for HR to act on without wasting most of the intervention budget. | G7: =IF(D7>=E7,"On/Above Target",IF(D7>=E7*0.85,"Near Target","Below Target")) -> On/Above Target | H7: The Logistic Regression model already meets this target (73.7%), meaning it is precise enough to operationalize as a monthly watch-list today.

Sheet Final_Report
A1: EMPLOYEE ATTRITION ANALYTICS: A DATA-DRIVEN INVESTIGATION OF VOLUNTARY TURNOVER AT A MULTI-DEPARTMENT ORGANIZATION
A2: A Data Analytics, Data Science and Business Intelligence Project | Dataset: IBM HR Analytics Employee Attrition & Performance (Kaggle)
A4: 1. EXECUTIVE SUMMARY
A5: This report presents an end-to-end analytics investigation of employee attrition using the IBM HR Analytics dataset (1,470 employees, 35 variables). The workforce's overall attrition rate stands at 16.1%, concentrated heavily among employees who work overtime (30.5% vs 10.4%), employees in their first two years of tenure (29.8%), and specific roles such as Sales Representative (39.8%). A supervised machine-learning pipeline comparing Logistic Regression, a Decision Tree and a Random Forest classifier found Logistic Regression to be the best-balanced model (Precision 73.7%, Recall 29.8%, F1 0.424, ROC-AUC 0.777), consistently ranking OverTime as the single strongest predictor of attrition across all three algorithms. Eleven business insights, four KPIs and a three-page Power BI dashboard blueprint translate these findings into a concrete, monitorable retention programme. The core recommendation is that overtime and workload management, not blanket compensation increases, represent the highest-return, lowest-cost lever available to reduce attrition.
A7: 2. DATASET DESCRIPTION
A8: The dataset used is IBM's HR Analytics Employee Attrition & Performance dataset, sourced from Kaggle (https://www.kaggle.com/datasets/pavansubhasht/ibm-hr-analytics-attrition-dataset). It contains 1,470 employee records across 35 variables spanning demographic (Age, Gender, MaritalStatus), compensation (MonthlyIncome, DailyRate, PercentSalaryHike, StockOptionLevel), tenure (YearsAtCompany, TotalWorkingYears, YearsSinceLastPromotion), satisfaction (JobSatisfaction, EnvironmentSatisfaction, WorkLifeBalance, RelationshipSatisfaction) and organizational (Department, JobRole, JobLevel, BusinessTravel) categories, with Attrition (Yes/No) as the target variable. Full column-level definitions and the working dataset are provided in the Dataset_Overview and Data_Cleaned tabs of this workbook.
A10: 3. DATASET JUSTIFICATION
A11: This dataset was selected because it satisfies every technical and analytical requirement of the brief: over 500 records (1,470), more than 8 columns (35), a genuine mix of numerical and categorical variables, embedded business metrics (MonthlyIncome, PerformanceRating, JobSatisfaction), and a binary target variable (Attrition) that is directly actionable by HR decision-makers. Full justification — business context, business problem, analytical objectives and expected business value — is documented in the Dataset_Overview tab. Because the native Kaggle file is unusually clean, realistic data-quality problems (missing values, duplicates, inconsistent categorical labels, incorrect data types and outliers) were deliberately injected into a working copy and fully documented, satisfying the assignment's data-cleaning requirements without misrepresenting the original source (see Data_RawIssues and Cleaning_Log).
A13: 4. DATA CLEANING AND PREPARATION
A14: Six categories of data-quality issues were identified and corrected in a documented Python (pandas/NumPy) pipeline, fully reproduced in the Cleaning_Log tab: (1) 40 missing values across MonthlyIncome, EnvironmentSatisfaction, Department, TotalWorkingYears and BusinessTravel, imputed using group-wise medians (numeric) or mode (categorical); (2) 15 exact duplicate employee records, removed via de-duplication on EmployeeNumber; (3) 21 inconsistent categorical labels (e.g. "sales"/"SALES"/"Sales ") standardized via a lookup-mapping function; (4) 10 numeric fields incorrectly typed as text (e.g. "35 years", "$5,993"), parsed back to numeric; (5) 8 statistical outliers (e.g. Age=202, MonthlyIncome=$999,999) identified via business-rule bounds and corrected via imputation or sign-correction; and (6) 2 additional scale-corruption errors discovered during verification (percentage values auto-converted to decimal fractions), corrected via a x100 rescaling rule. The cleaned, feature-engineered dataset (1,470 unique employees, 47 columns including 10 engineered features such as SatisfactionIndex, IncomeBand and TenureRatio) is provided in Data_Cleaned. AI-assisted recommendations for preventing these issues at the source system are documented at the foot of the Cleaning_Log tab.
A16: 5. EXPLORATORY DATA ANALYSIS
A17: Full exploratory analysis — summary statistics, missing-value verification, distribution histograms, a box-and-whisker income comparison, a correlation heatmap, category comparisons, tenure-trend analysis, grouped aggregations and a target-variable breakdown — is provided in the EDA_Summary tab with seven supporting charts. Headline findings: the workforce skews toward the 25-44 age band; MonthlyIncome is right-skewed with a small number of high-earner outliers visible in the box plot; and OverTime shows the strongest correlation with Attrition (r=0.245) of any variable measured, ahead of MonthlyIncome (r=-0.158), Age (r=-0.162) and TotalWorkingYears (r=-0.167). Nine explicit business questions (e.g. "Does overtime drive attrition?", "Is attrition concentrated in early tenure?") are answered directly with supporting evidence at the foot of the EDA_Summary tab.
... A38: This project demonstrates a complete analytics lifecycle — from data cleaning and exploratory analysis through predictive modelling, KPI definition and dashboard design — applied to a genuine business problem with material financial stakes. The evidence consistently points to overtime and early-tenure disengagement as the two most actionable drivers of attrition, ahead of compensation and demographic factors. With three of four KPIs currently below target, the organisation has clear, quantified room for improvement, and the Logistic Regression model provides a ready-to-use tool for prioritizing where to intervene first. Subsequent work should focus on piloting the overtime-reduction recommendation, tracking its effect on the KPI dashboard, and progressively enriching the dataset (e.g. adding hire dates and location) to support true time-series and geographic analysis in future iterations.
